[{"n":"具志堅用高記念館","la":24.34979,"lo":124.14617,"c":"spot","t":["博物館藝術"],"s":90,"wt":"具志堅用高記念館","ad":"沖縄県石垣市新川","oh":"Mo-Su 09:00-17:00","w":"https://yaeyama.or.jp/具志堅用高記念館/"},{"n":"石垣市立八重山博物館","la":24.33804,"lo":124.15978,"c":"spot","t":["博物館藝術"],"s":90,"wt":"石垣市立八重山博物館","ad":"沖縄県石垣市字登野城","oh":"Mo-Su 09:00-17:00","w":"https://www.city.ishigaki.okinawa.jp/400000/410000/410500/top.html"},{"n":"石垣やいま村","la":24.40369,"lo":124.14395,"c":"spot","t":["博物館藝術"],"s":90,"wt":"石垣やいま村","oh":"Mo-Su 09:00-17:30","w":"https://www.yaimamura.com/"},{"n":"唐人墓","la":24.3657,"lo":124.11335,"c":"spot","t":["歷史古蹟"],"s":45,"wt":"唐人墓","w":"https://www.city.ishigaki.okinawa.jp/100000/100500/ishigaki_fuukei_rekishi/123.html"},{"n":"石垣鐘乳石洞","la":24.36185,"lo":124.15434,"c":"spot","s":60,"wt":"石垣島鍾乳洞","w":"https://www.ishigaki-cave.com/"},{"n":"バンナ公園","la":24.37864,"lo":124.17616,"c":"spot","t":["自然風景"],"s":45,"ad":"沖縄県石垣市登野城","oh":"Mo-Su 09:00-21:00"},{"n":"サタケ八重山ヤシ記念館","la":24.45193,"lo":124.19396,"c":"spot","t":["博物館藝術"],"s":90,"oh":"09:00-17:00","w":"https://satake-japan.co.jp/index.html"},{"n":"米原のヤエヤマヤシ群落","la":24.45089,"lo":124.19495,"c":"spot","t":["自然風景"],"s":45,"w":"https://www.city.ishigaki.okinawa.jp/100000/100500/ishigaki_fuukei_rekishi/084.html"},{"n":"於茂登岳","la":24.42724,"lo":124.18342,"c":"spot","t":["自然風景","夜景展望"],"s":60,"wt":"於茂登岳"},{"n":"桃林寺","la":24.34375,"lo":124.15552,"c":"spot","t":["神社寺廟"],"s":30,"wt":"桃林寺 (石垣市)"},{"n":"桴海於茂登岳","la":24.44213,"lo":124.19401,"c":"spot","t":["自然風景","夜景展望"],"s":60,"wt":"桴海於茂登岳"},{"n":"ぶざま岳","la":24.42688,"lo":124.14154,"c":"spot","t":["自然風景","夜景展望"],"s":60,"wt":"ぶざま岳"},{"n":"野底岳","la":24.48892,"lo":124.24872,"c":"spot","t":["自然風景","夜景展望"],"s":60,"wt":"野底岳"},{"n":"安良岳","la":24.57209,"lo":124.31399,"c":"spot","t":["自然風景","夜景展望"],"s":60,"wt":"安良岳 (沖縄県)"},{"n":"カーラ岳","la":24.40909,"lo":124.24856,"c":"spot","t":["自然風景","夜景展望"],"s":60,"wt":"カラ岳"},{"n":"名蔵湾红树林","la":24.4129,"lo":124.14404,"c":"spot","j":"名蔵湾マングローブ林","s":60,"w":"https://www.manglobal.or.jp"},{"n":"コンドイビーチ","la":24.32541,"lo":124.07802,"c":"spot","t":["自然風景","親子同樂"],"s":90,"wt":"コンドイ浜"},{"n":"730シィーシィーパーク","la":24.33831,"lo":124.15743,"c":"spot","t":["自然風景"],"s":45,"wt":"730シィーシィーパーク"},{"n":"宮良殿內","la":24.34122,"lo":124.15973,"c":"spot","j":"宮良殿内","t":["自然風景"],"s":45},{"n":"玉取崎","la":24.49111,"lo":124.27742,"c":"spot","t":["自然風景","夜景展望"],"s":40},{"n":"川平公園","la":24.46133,"lo":124.14303,"c":"spot","t":["自然風景","夜景展望"],"s":40},{"n":"龍神鍾乳洞","la":24.36017,"lo":124.15503,"c":"spot","s":60},{"n":"米子燒工房","la":24.45325,"lo":124.18712,"c":"spot","s":60},{"n":"730記念碑","la":24.33834,"lo":124.15743,"c":"spot","t":["歷史古蹟"],"s":45},{"n":"玉取崎展望台","la":24.49054,"lo":124.27887,"c":"spot","t":["自然風景","夜景展望"],"s":40},{"n":"具志堅用高氏像","la":24.33696,"lo":124.15545,"c":"spot","t":["歷史古蹟"],"s":45},{"n":"Baravido Kanko Farm","la":24.37676,"lo":124.18026,"c":"spot","s":60,"w":"www.tafukunoen.com"},{"n":"屋良部岳","la":24.43944,"lo":124.08628,"c":"spot","t":["自然風景","夜景展望"],"s":60},{"n":"川平ウフ岳","la":24.43543,"lo":124.16219,"c":"spot","t":["自然風景","夜景展望"],"s":60},{"n":"高間山","la":24.44324,"lo":124.21055,"c":"spot","t":["自然風景","夜景展望"],"s":60},{"n":"ホゥラ岳","la":24.44528,"lo":124.22412,"c":"spot","t":["自然風景","夜景展望"],"s":60},{"n":"大野岳","la":24.48674,"lo":124.266,"c":"spot","t":["自然風景","夜景展望"],"s":60},{"n":"金武岳","la":24.49309,"lo":124.27361,"c":"spot","t":["自然風景","夜景展望"],"s":60},{"n":"大浦山","la":24.50746,"lo":124.26328,"c":"spot","t":["自然風景","夜景展望"],"s":60},{"n":"はんな岳","la":24.52226,"lo":124.28893,"c":"spot","t":["自然風景","夜景展望"],"s":60},{"n":"荒川瀑布","la":24.44709,"lo":124.17975,"c":"spot","s":60},{"n":"砂之道","la":24.44615,"lo":124.1512,"c":"spot","s":60},{"n":"山当山","la":24.59232,"lo":124.32604,"c":"spot","t":["自然風景","夜景展望"],"s":60},{"n":"トムル岳","la":24.52976,"lo":124.30012,"c":"spot","t":["自然風景","夜景展望"],"s":60},{"n":"前嵩","la":24.45667,"lo":124.1276,"c":"spot","t":["自然風景","夜景展望"],"s":60},{"n":"嵩田山","la":24.40134,"lo":124.1768,"c":"spot","t":["自然風景","夜景展望"],"s":60},{"n":"バンナ岳","la":24.37242,"lo":124.16377,"c":"spot","t":["自然風景","夜景展望"],"s":60},{"n":"前勢岳","la":24.37291,"lo":124.13967,"c":"spot","t":["自然風景","夜景展望"],"s":60},{"n":"川平貝塚","la":24.46694,"lo":124.13272,"c":"spot","t":["歷史古蹟"],"s":45},{"n":"舟蔵公園","la":24.35453,"lo":124.13547,"c":"spot","t":["自然風景"],"s":45},{"n":"底地ビーチ","la":24.46483,"lo":124.12252,"c":"spot","t":["自然風景","親子同樂"],"s":90},{"n":"米原ビーチ","la":24.45235,"lo":124.18504,"c":"spot","t":["自然風景","親子同樂"],"s":90},{"n":"アンパル塔","la":24.40409,"lo":124.14361,"c":"spot","t":["自然風景","夜景展望"],"s":40},{"n":"電信屋跡","la":24.42078,"lo":124.08615,"c":"spot","t":["歷史古蹟"],"s":45},{"n":"創価学会八重山文化会館","la":24.3655,"lo":124.14165,"c":"spot","t":["神社寺廟"],"s":30,"ad":"沖縄県石垣市"},{"n":"石垣宝来宝来神社","la":24.35698,"lo":124.16552,"c":"spot","t":["神社寺廟"],"s":30,"ad":"沖縄県石垣市大川宇志原1134-1"},{"n":"真栄里公園","la":24.3325,"lo":124.16915,"c":"spot","t":["自然風景"],"s":45},{"n":"石垣市中央運動公園","la":24.34295,"lo":124.17592,"c":"spot","t":["自然風景"],"s":45},{"n":"フルスト原遺跡","la":24.35027,"lo":124.19547,"c":"spot","t":["歷史古蹟"],"s":45,"wt":"フルスト原遺跡"},{"n":"フサキビーチ","la":24.37261,"lo":124.11556,"c":"spot","t":["自然風景","親子同樂"],"s":90},{"n":"はいむるぶしビーチ","la":24.32767,"lo":124.00299,"c":"spot","t":["自然風景","親子同樂"],"s":90},{"n":"皆治浜","la":24.31945,"lo":124.07724,"c":"spot","t":["自然風景","親子同樂"],"s":90},{"n":"サザンゲート公園","la":24.33072,"lo":124.15832,"c":"spot","t":["自然風景"],"s":45},{"n":"アイヤル浜","la":24.32007,"lo":124.10006,"c":"spot","t":["自然風景","親子同樂"],"s":90},{"n":"キトッチ浜","la":24.3228,"lo":124.10071,"c":"spot","t":["自然風景","親子同樂"],"s":90},{"n":"ナーラサ浜","la":24.32679,"lo":124.0993,"c":"spot","t":["自然風景","親子同樂"],"s":90},{"n":"新里村遺跡","la":24.33773,"lo":124.08977,"c":"spot","t":["歷史古蹟"],"s":45},{"n":"カンナージ浜","la":24.31864,"lo":124.09747,"c":"spot","t":["自然風景","親子同樂"],"s":90},{"n":"サンセットビーチ","la":24.56184,"lo":124.28395,"c":"spot","t":["自然風景","親子同樂"],"s":90},{"n":"白保海岸","la":24.35456,"lo":124.24552,"c":"spot","t":["自然風景","親子同樂"],"s":90},{"n":"Saaji Ori","la":24.32817,"lo":124.08579,"c":"spot","t":["神社寺廟"],"s":30},{"n":"西塘御嶽","la":24.33009,"lo":124.08646,"c":"spot","t":["神社寺廟"],"s":30},{"n":"Folkcraft Museum","la":24.33141,"lo":124.08573,"c":"spot","j":"竹富民芸館","t":["博物館藝術"],"s":90},{"n":"喜宝院蒐集館","la":24.33174,"lo":124.08405,"c":"spot","t":["博物館藝術"],"s":90},{"n":"啓蒙壷","la":24.32916,"lo":124.08719,"c":"spot","t":["歷史古蹟"],"s":45},{"n":"東パイザーシ御嶽","la":24.32918,"lo":124.0871,"c":"spot","t":["神社寺廟"],"s":30},{"n":"石垣島サイエンスガーデン","la":24.44906,"lo":124.13455,"c":"spot","t":["自然風景"],"s":45},{"n":"石垣島ビール","la":24.36337,"lo":124.14226,"c":"spot","t":["美酒微醺"],"s":60},{"n":"Kabira Bay","la":24.4528,"lo":124.14384,"c":"spot","j":"川平湾","s":60},{"n":"先島諸島火番盛(小城盛)","la":24.33229,"lo":124.08596,"c":"spot","t":["歷史古蹟"],"s":45},{"n":"蔵元跡","la":24.31987,"lo":124.07744,"c":"spot","t":["歷史古蹟"],"s":45},{"n":"先島諸島火番盛(水納遠見)","la":24.75245,"lo":124.70401,"c":"spot","t":["歷史古蹟"],"s":45},{"n":"先島諸島火番盛(八重山遠見)","la":24.67168,"lo":124.69649,"c":"spot","t":["歷史古蹟"],"s":45},{"n":"先島諸島火番盛(宮古遠見)","la":24.67391,"lo":124.70297,"c":"spot","t":["歷史古蹟"],"s":45},{"n":"川平夕バガ一","la":24.47462,"lo":124.13487,"c":"spot","s":60},{"n":"バンナ岳南口","la":24.36854,"lo":124.1573,"c":"spot","t":["自然風景","夜景展望"],"s":40},{"n":"前勢岳展望台","la":24.37006,"lo":124.1479,"c":"spot","t":["自然風景","夜景展望"],"s":40},{"n":"於茂登岳登山口","la":24.41738,"lo":124.18918,"c":"spot","t":["自然風景","夜景展望"],"s":40},{"n":"渡り鳥観察所","la":24.38374,"lo":124.16696,"c":"spot","t":["自然風景","夜景展望"],"s":40},{"n":"ヒルギ群落","la":24.48549,"lo":124.23211,"c":"spot","t":["自然風景","夜景展望"],"s":40},{"n":"川平観音堂","la":24.46114,"lo":124.14284,"c":"spot","t":["神社寺廟"],"s":30},{"n":"川平公園展望台","la":24.4604,"lo":124.14288,"c":"spot","t":["自然風景","夜景展望"],"s":40},{"n":"赤イロ目宮鳥御嶽","la":24.46302,"lo":124.13765,"c":"spot","t":["神社寺廟"],"s":30},{"n":"日蓮正宗唱行寺","la":24.35978,"lo":124.15769,"c":"spot","t":["神社寺廟"],"s":30},{"n":"群星御嶽","la":24.46578,"lo":124.13139,"c":"spot","t":["神社寺廟"],"s":30},{"n":"底原ダム","la":24.4205,"lo":124.21451,"c":"spot","t":["自然風景","夜景展望"],"s":40},{"n":"名蔵ダム","la":24.41083,"lo":124.17602,"c":"spot","t":["自然風景","夜景展望"],"s":40},{"n":"国立天文台VERA石垣島観測局電波望遠鏡","la":24.41233,"lo":124.17136,"c":"spot","t":["自然風景","夜景展望"],"s":40},{"n":"石垣ダム","la":24.37987,"lo":124.17833,"c":"spot","t":["自然風景","夜景展望"],"s":40},{"n":"真栄里ダム","la":24.41811,"lo":124.20687,"c":"spot","t":["自然風景","夜景展望"],"s":40},{"n":"石垣空港","la":24.38947,"lo":124.24623,"c":"spot","t":["自然風景","夜景展望"],"s":40},{"n":"世持御嶽","la":24.33178,"lo":124.08566,"c":"spot","t":["神社寺廟"],"s":30},{"n":"さうすぽいんとダイビンク","la":24.46064,"lo":124.14186,"c":"spot","t":["自然風景","夜景展望"],"s":40},{"n":"しらほサンゴ村","la":24.35117,"lo":124.24202,"c":"spot","t":["自然風景","夜景展望"],"s":40},{"n":"Hirakubozaki","la":24.61027,"lo":124.31606,"c":"spot","j":"平久保崎","t":["自然風景","夜景展望"],"s":40},{"n":"Nei Museum of Art","la":24.36684,"lo":124.11332,"c":"spot","j":"八重山友禅染め ネイギャラリー 石垣島","t":["博物館藝術"],"s":60},{"n":"石垣島東海岸の津波石群津波大石","la":24.34595,"lo":124.20029,"c":"spot","t":["歷史古蹟"],"s":45},{"n":"明和大津波遭難者慰霊之塔","la":24.36476,"lo":124.22003,"c":"spot","t":["歷史古蹟"],"s":45},{"n":"あかやま展望台","la":24.33109,"lo":124.08541,"c":"spot","t":["自然風景","夜景展望"],"s":40},{"n":"崎山毅先生記念碑","la":24.33034,"lo":124.08659,"c":"spot","t":["歷史古蹟"],"s":45},{"n":"聖女 安里屋クヤマ之墓","la":24.33584,"lo":124.08197,"c":"spot","t":["歷史古蹟"],"s":45},{"n":"山城善三先生記念碑","la":24.33009,"lo":124.08626,"c":"spot","t":["歷史古蹟"],"s":45},{"n":"上間廣起先生記念碑","la":24.33171,"lo":124.08549,"c":"spot","t":["歷史古蹟"],"s":45},{"n":"水道記念碑","la":24.32734,"lo":124.08667,"c":"spot","t":["歷史古蹟"],"s":45},{"n":"人頭税廃止百年記念の碑","la":24.32726,"lo":124.08673,"c":"spot","t":["歷史古蹟"],"s":45},{"n":"幸本御嶽","la":24.32601,"lo":124.08629,"c":"spot","t":["神社寺廟"],"s":30},{"n":"ニーラン神石","la":24.32789,"lo":124.07916,"c":"spot","t":["歷史古蹟"],"s":45},{"n":"久間原御嶽","la":24.3279,"lo":124.09175,"c":"spot","t":["神社寺廟"],"s":30},{"n":"健康モデル指定地区標示塔","la":24.3351,"lo":124.09343,"c":"spot","t":["歷史古蹟"],"s":45},{"n":"フナヤー跡","la":24.33529,"lo":124.09325,"c":"spot","t":["歷史古蹟"],"s":45},{"n":"美崎御嶽","la":24.33977,"lo":124.08728,"c":"spot","t":["神社寺廟"],"s":30},{"n":"先島諸島火番盛","la":24.46834,"lo":124.1322,"c":"spot","t":["歷史古蹟"],"s":45},{"n":"wall ruin","la":24.45151,"lo":124.15883,"c":"spot","t":["歷史古蹟"],"s":45},{"n":"神社","la":24.45091,"lo":124.159,"c":"spot","t":["歷史古蹟"],"s":45},{"n":"house and wall ruin","la":24.45195,"lo":124.16023,"c":"spot","t":["歷史古蹟"],"s":45},{"n":"??祈跡","la":24.32815,"lo":124.08674,"c":"spot","t":["歷史古蹟"],"s":45},{"n":"Kabira Ishizaki manta scramble","la":24.48723,"lo":124.11705,"c":"spot","s":60},{"n":"喜宝院 布教所","la":24.33162,"lo":124.08451,"c":"spot","t":["神社寺廟"],"s":30},{"n":"WWF総裁 エシンハラ公フィリップ殿下 白保訪問記念","la":24.35454,"lo":124.24542,"c":"spot","t":["歷史古蹟"],"s":45},{"n":"舟溝開砕記念の塔","la":24.35455,"lo":124.24542,"c":"spot","t":["歷史古蹟"],"s":45},{"n":"キノコ岩","la":24.52349,"lo":124.28152,"c":"spot","t":["歷史古蹟"],"s":45},{"n":"ヌスクオン","la":24.49592,"lo":124.23101,"c":"spot","t":["神社寺廟"],"s":30},{"n":"多田浜海岸","la":24.33129,"lo":124.18348,"c":"spot","t":["自然風景","親子同樂"],"s":90},{"n":"轟ビーチ","la":24.38339,"lo":124.25203,"c":"spot","t":["自然風景","親子同樂"],"s":90},{"n":"伊土名ビーチ","la":24.48201,"lo":124.22446,"c":"spot","t":["自然風景","親子同樂"],"s":90},{"n":"明石ビーチ","la":24.53947,"lo":124.30302,"c":"spot","t":["自然風景","親子同樂"],"s":90},{"n":"平野ビーチ","la":24.60652,"lo":124.32682,"c":"spot","t":["自然風景","親子同樂"],"s":90},{"n":"真栄里ビーチ","la":24.33387,"lo":124.18908,"c":"spot","t":["自然風景","親子同樂"],"s":90},{"n":"大浜海岸","la":24.35311,"lo":124.19942,"c":"spot","t":["自然風景","親子同樂"],"s":90},{"n":"アカフチ","la":24.51012,"lo":124.28186,"c":"spot","t":["歷史古蹟"],"s":45},{"n":"マキ石（ハート石）","la":24.50717,"lo":124.28322,"c":"spot","s":60},{"n":"バリ石","la":24.51997,"lo":124.29945,"c":"spot","s":60},{"n":"旧與那國家住宅","la":24.32857,"lo":124.08748,"c":"spot","t":["歷史古蹟"],"s":45},{"n":"Yashima Ryokushi Park","la":24.33458,"lo":124.15831,"c":"spot","t":["自然風景"],"s":45},{"n":"竹富島伝統的建造物保存地区","la":24.32777,"lo":124.08879,"c":"spot","t":["歷史古蹟"],"s":45},{"n":"Waterfowl viewpoint","la":24.38107,"lo":124.1774,"c":"spot","t":["自然風景","夜景展望"],"s":40},{"n":"Crystal Beach","la":24.44758,"lo":124.17454,"c":"spot","j":"山原川のビーチ","t":["自然風景","親子同樂"],"s":90},{"n":"Tommy Beach","la":24.44912,"lo":124.17663,"c":"spot","t":["自然風景","親子同樂"],"s":90},{"n":"Ishizaki beach","la":24.48169,"lo":124.12016,"c":"spot","t":["自然風景","親子同樂"],"s":90},{"n":"Hirari Island beach","la":24.48125,"lo":124.11551,"c":"spot","t":["自然風景","親子同樂"],"s":90},{"n":"冨崎観音堂","la":24.36489,"lo":124.11586,"c":"spot","t":["神社寺廟"],"s":30},{"n":"やどかり公園","la":24.3311,"lo":124.17823,"c":"spot","t":["自然風景"],"s":45},{"n":"ケンタッキーフライドチキン","la":24.3481,"lo":124.1473,"c":"food","ad":"沖縄県石垣市新栄町","cu":"chicken","oh":"Mo-Su 11:00-21:00","w":"https://search.kfc.co.jp/map/801"},{"n":"川平ファーム","la":24.45049,"lo":124.13409,"c":"food","ad":"石垣市川平1291-63","cu":"juice","oh":"10:00-18:00","w":"https://www.passion-jp.com/"},{"n":"舟蔵の里","la":24.35647,"lo":124.13037,"c":"food","ad":"沖縄県石垣市新川","cu":"regional","oh":"11:00-22:00; We off","w":"https://www.funakuranosato.com/"},{"n":"やっぱりステーキ","la":24.34309,"lo":124.15354,"c":"food","ad":"沖縄県石垣市新栄町","cu":"steak_house","w":"https://yapparigroup.jp/shop/ishigaki.html"},{"n":"Blue Cafe","la":24.33746,"lo":124.15803,"c":"food","ad":"沖縄県石垣市美崎町","cu":"bakery","oh":"07:00-15:00","w":"https://bluecabin-ishigakijima.jp/cafe/"},{"n":"島創作料理 居酒屋 うるま","la":24.33826,"lo":124.15638,"c":"food","ad":"沖縄県石垣市美崎町","cu":"japanese;sushi;seafood;regional","oh":"Fr-We 18:00-23:00","w":"https://izakayauruma.wixsite.com/website/?lang=ja"},{"n":"やいま家庭料理 さつき","la":24.33858,"lo":124.1552,"c":"food","ad":"沖縄県石垣市美崎町","cu":"regional","oh":"Mo-Su 17:00-22:00","w":"https://www.miyahira.co.jp/restaurant/satsuki.html"},{"n":"cafe & restaurant OHAMA","la":24.33508,"lo":124.15934,"c":"food","ad":"沖縄県石垣市八島町一丁目","cu":"buffet","oh":"Mo-Su 06:30-10:30","w":"https://www.apahotel.com/hotel/kyushu-okinawa/okinawa/ishigakijima/restaurant_01/"},{"n":"大戶屋","la":24.33661,"lo":124.18158,"c":"food","j":"大戸屋","cu":"japanese","oh":"Mo-Su 11:00-22:30"},{"n":"ぱいかじ","la":24.33902,"lo":124.15812,"c":"food","ad":"石垣市","cu":"japanese","oh":"17:00-24:00"},{"n":"A&W","la":24.33886,"lo":124.15746,"c":"food","j":"A&W石垣店","cu":"burger","w":"https://www.awok.co.jp/"},{"n":"三線ライブcafe&diningゆにば","la":24.33963,"lo":124.15887,"c":"food","ad":"石垣市","cu":"japanese;okinawan","oh":"18:00-24:00"},{"n":"炭火燒肉 たけさん亭","la":24.34084,"lo":124.15167,"c":"food","ad":"沖縄県石垣市浜崎町二丁目","cu":"barbecue","oh":"We-Mo 17:00-21:00"},{"n":"夢乃屋","la":24.3381,"lo":124.15757,"c":"food","ad":"沖縄県石垣市美崎町","cu":"regional","oh":"Mo-Su 11:00-21:00"},{"n":"そば家 なかもと","la":24.46182,"lo":124.1419,"c":"food","cu":"ramen","oh":"Mo-Su 11:00-15:00"},{"n":"海人居酒屋 源","la":24.3447,"lo":124.15172,"c":"food","ad":"沖縄県石垣市新栄町","oh":"Mo-Sa 15:50-23:00","w":"http://ishigaki-gen.com/page/shinei"},{"n":"もんじゃー・マン","la":24.34195,"lo":124.15586,"c":"food","j":"もんじゃーマン","cu":"japanese","oh":"Th-Tu 17:00-05:00"},{"n":"あっき","la":24.34017,"lo":124.1531,"c":"food","cu":"japanese","oh":"Th-Tu 17:00-23:00"},{"n":"石田屋","la":24.33844,"lo":124.1577,"c":"food","cu":"japanese","oh":"Mo-Su 11:30-23:00"},{"n":"中村屋","la":24.3456,"lo":124.15769,"c":"food","cu":"curry","oh":"Th-Tu 11:30-14:30"},{"n":"ぬちぐさカフェ","la":24.36726,"lo":124.11968,"c":"food","ad":"沖縄県石垣市新川","oh":"Mo-Su 11:00-16:00","w":"https://yoga.okinawa/cafe/"},{"n":"日本料理郷土料理 ひるぎ","la":24.33862,"lo":124.15522,"c":"food","ad":"沖縄県石垣市美崎町","cu":"japanese;regional","w":"https://www.miyahira.co.jp/restaurant/hirugi.html"},{"n":"ティーラウンジ カトレア","la":24.33844,"lo":124.15519,"c":"food","ad":"沖縄県石垣市美崎町","cu":"cake;ice_cream;juice;tea","oh":"Mo-Su 10:00-17:00"},{"n":"ぱぱや","la":24.4516,"lo":124.19515,"c":"food","oh":"08:30-18:00"},{"n":"Tony Soba","la":24.34051,"lo":124.1567,"c":"food","j":"栄福食堂（トニーそば）","cu":"japanese","w":"https://www.tripadvisor.it/Restaurant_Review-g298223-d4743412-Reviews-Tony_Soba_Eifuku_Shokudo-Ishigaki_Okinawa_Prefecture_Kyushu_Okinawa.html"},{"n":"石垣シーサイドホテル","la":24.47176,"lo":124.12587,"c":"food","ad":"石垣市川平","cu":"international"},{"n":"クラブメッドカビラ","la":24.47995,"lo":124.12056,"c":"food","ad":"石垣市川平","cu":"international"},{"n":"やし屋","la":24.45181,"lo":124.19494,"c":"food","oh":"11:30-18:00"},{"n":"石垣牛專賣店","la":24.34161,"lo":124.1613,"c":"food","oh":"Mo-Su 10:00-20:00"},{"n":"月桃庵","la":24.33853,"lo":124.1552,"c":"food","ad":"沖縄県石垣市美崎町","cu":"steak_house"},{"n":"とうふの比嘉","la":24.35354,"lo":124.16038,"c":"food","oh":"Mo-Sa 06:30-10:00"},{"n":"なかよし食堂","la":24.34493,"lo":124.15201,"c":"food","oh":"Th-Tu 11:30-19:30"},{"n":"Kabiraごはん屋","la":24.46152,"lo":124.14153,"c":"food","oh":"Mo-Sa 11:00-14:30"},{"n":"来夏世","la":24.34554,"lo":124.15926,"c":"food","cu":"soba","oh":"Mo-Sa 11:00-14:00"},{"n":"うーまる","la":24.4619,"lo":124.14092,"c":"food","cu":"okonomiyaki"},{"n":"おいシーサー遇(ジェラート)","la":24.46164,"lo":124.14178,"c":"food","cu":"ramen"},{"n":"じんべい","la":24.46169,"lo":124.14156,"c":"food","cu":"sushi"},{"n":"花あかり","la":24.33975,"lo":124.15552,"c":"food","ad":"沖縄県石垣市美崎町","oh":"Mo-Su 20:00-24:00"},{"n":"鮨人（すしんちゅ）","la":24.33588,"lo":124.18481,"c":"food","cu":"sushi"},{"n":"ほっともっと","la":24.3335,"lo":124.16619,"c":"food","cu":"japanese"},{"n":"ほっともっと登野城小学校前店","la":24.34404,"lo":124.16491,"c":"food","w":"http://hottomotto.com"},{"n":"海カフェ キッチン セント エルモ","la":24.36468,"lo":124.11372,"c":"food","j":"海カフェ&キッチン セント エルモ","cu":"italian"},{"n":"海の見える食堂フサキガーデンテラス","la":24.36393,"lo":124.11547,"c":"food","cu":"friture;japanese;regional;soba;local"},{"n":"e:ma ISHIGAKIJIMA TABISHIKA Hotel","la":24.33704,"lo":124.15985,"c":"food","j":"エーマ　石垣島タビシカ　ホテル","ad":"沖縄県石垣市字登野城","w":"https://ema-hotels.com/tabishika/"},{"n":"Pizzeria il Trecorde","la":24.34128,"lo":124.1569,"c":"food","j":"ピッツェリア　イル　トレコルデ","cu":"italian","oh":"Mo-Sa 11:30-14:00,17:00-22:30; Su off"},{"n":"Native DELi","la":24.33916,"lo":124.15748,"c":"food","ad":"沖縄県石垣市","cu":"steak_house"},{"n":"トレアドール","la":24.33849,"lo":124.15518,"c":"food","ad":"沖縄県石垣市美崎町","cu":"buffet"},{"n":"琉球の爺","la":24.34119,"lo":124.15209,"c":"food","ad":"沖縄県石垣市浜崎町２丁目","cu":"regional"},{"n":"LENTO","la":24.33682,"lo":124.18931,"c":"food","cu":"japanese","w":"https://lento-ishigaki.com/"},{"n":"-","la":24.33937,"lo":124.15767,"c":"food","cu":"japanese"},{"n":"Champる","la":24.33929,"lo":124.15718,"c":"food","cu":"fish"},{"n":"達屋","la":24.33975,"lo":124.15685,"c":"food","cu":"noodle"},{"n":"焼肉ステーションガストロ","la":24.34009,"lo":124.19031,"c":"food","cu":"japanese"},{"n":"やいま村","la":24.40431,"lo":124.14487,"c":"food","cu":"regional"},{"n":"ミスタードーナツ","la":24.34202,"lo":124.16666,"c":"food","cu":"coffee_shop"},{"n":"担たん亭","la":24.36156,"lo":124.14272,"c":"food","cu":"regional"},{"n":"一休食堂","la":24.36261,"lo":124.15716,"c":"food","cu":"regional"},{"n":"Pizza Parco","la":24.34197,"lo":124.15513,"c":"food","cu":"pizza"},{"n":"石垣島きたうち牧場 ハンバーガー店","la":24.33815,"lo":124.1559,"c":"food","cu":"burger"},{"n":"邊銀食堂","la":24.34014,"lo":124.15848,"c":"food","j":"辺銀食堂"},{"n":"がきや","la":24.49907,"lo":124.2458,"c":"food","oh":"Fr-Tu"},{"n":"島の駅 カビラガーデン","la":24.46115,"lo":124.14223,"c":"food"},{"n":"ちろりん村","la":24.32523,"lo":124.08624,"c":"food"},{"n":"ちゃんぷるcafe","la":24.46057,"lo":124.14246,"c":"food"},{"n":"食堂","la":24.33731,"lo":124.16633,"c":"food"},{"n":"あさひ食堂","la":24.34153,"lo":124.16229,"c":"food"},{"n":"Setsukaya","la":24.46218,"lo":124.13779,"c":"food","cu":"japanese"},{"n":"Pulau","la":24.46311,"lo":124.13929,"c":"food","cu":"indonesian"},{"n":"島たい焼き本舗","la":24.33733,"lo":124.16916,"c":"food"},{"n":"beef burger","la":24.5573,"lo":124.28743,"c":"food","cu":"burger"},{"n":"Yone Yashi","la":24.45183,"lo":124.19523,"c":"food","j":"よねやし"},{"n":"Italico","la":24.43982,"lo":124.10906,"c":"food","cu":"italian"},{"n":"ハートらんど","la":24.25295,"lo":124.00156,"c":"food"},{"n":"うんどうや","la":24.23632,"lo":124.01456,"c":"food","cu":"soba"},{"n":"友利ストアー","la":24.34268,"lo":124.15105,"c":"food","cu":"japanese"},{"n":"まるひろ鮮魚店","la":24.34357,"lo":124.15304,"c":"food","cu":"seafood"},{"n":"ダイニング英","la":24.35095,"lo":124.24201,"c":"food"},{"n":"島の麺飯処 琉家 石垣島店","la":24.33307,"lo":124.17334,"c":"food","cu":"chinese"},{"n":"石垣島食堂","la":24.36187,"lo":124.1542,"c":"food","j":"Ishigakijima Restaurant"},{"n":"とぅもーるショップ","la":24.33725,"lo":124.15506,"c":"food","ad":"沖縄県石垣市美崎町"},{"n":"郷土料理 しゃち","la":24.34003,"lo":124.14968,"c":"food","cu":"regional"},{"n":"燒肉龍球","la":24.33968,"lo":124.14985,"c":"food","cu":"barbecue"},{"n":"レストラン花茶屋","la":24.34255,"lo":124.15132,"c":"food","cu":"buffet"},{"n":"Tamatorizaki Gateway","la":24.49162,"lo":124.27719,"c":"food","oh":"Mo-Su 10:00-16:00"},{"n":"焼肉　石垣島大昌園","la":24.34431,"lo":124.18114,"c":"food","ad":"沖縄県石垣市真栄里"},{"n":"ガーデンあさひ","la":24.33136,"lo":124.08225,"c":"food"},{"n":"そば処 竹の子","la":24.3313,"lo":124.08353,"c":"food"},{"n":"ヴィラ別邸","la":24.32406,"lo":124.08747,"c":"food"},{"n":"やらぼ","la":24.33177,"lo":124.08384,"c":"food"},{"n":"お食事処 かにふ","la":24.32984,"lo":124.08743,"c":"food"},{"n":"cafe","la":24.33125,"lo":124.17473,"c":"food"},{"n":"南国の華","la":24.33717,"lo":124.15831,"c":"food"},{"n":"HItoshi","la":24.34449,"lo":124.15249,"c":"food","j":"ひとし本店"},{"n":"Kabira cafe","la":24.45931,"lo":124.1404,"c":"food"},{"n":"VANILLA DELI漢堡店","la":24.3407,"lo":124.15631,"c":"food"},{"n":"嵩田植物園","la":24.4071,"lo":124.17306,"c":"food"},{"n":"川平公園茶屋","la":24.46033,"lo":124.14246,"c":"food"},{"n":"かびら食堂","la":24.46119,"lo":124.14247,"c":"food"},{"n":"Joo Chiat Café","la":24.45946,"lo":124.14008,"c":"food"},{"n":"石垣商店","la":24.43925,"lo":124.11826,"c":"food"},{"n":"ガーデンパナ","la":24.43929,"lo":124.11794,"c":"food"},{"n":"新川食堂","la":24.34994,"lo":124.14584,"c":"food"},{"n":"MOS Burger Ishigaki Maezato Shop","la":24.33756,"lo":124.18091,"c":"food"},{"n":"あんぶれら","la":24.34238,"lo":124.17465,"c":"food"},{"n":"源　総本店","la":24.34116,"lo":124.15743,"c":"food"},{"n":"石垣島料理丸八","la":24.34486,"lo":124.1813,"c":"food"},{"n":"新垣食堂","la":24.5104,"lo":124.28334,"c":"food"},{"n":"キミ食堂","la":24.34174,"lo":124.16654,"c":"food"},{"n":"明石食堂","la":24.53949,"lo":124.30021,"c":"food"},{"n":"オリジン","la":24.34154,"lo":124.15613,"c":"food"},{"n":"焼き肉オリオン","la":24.34174,"lo":124.15616,"c":"food"},{"n":"バニラデリ","la":24.34076,"lo":124.15668,"c":"food"},{"n":"魚仁","la":24.34166,"lo":124.15602,"c":"food"},{"n":"石垣島きたうち牧場 浜崎本店","la":24.33994,"lo":124.15019,"c":"food"},{"n":"ふるさと食堂","la":24.33515,"lo":124.18029,"c":"food"},{"n":"Kuwachii","la":24.3379,"lo":124.14918,"c":"food"},{"n":"パーラー ぱいぬ島","la":24.33139,"lo":124.08599,"c":"food"},{"n":"R's Cafe","la":24.45948,"lo":124.14154,"c":"food"},{"n":"Kaboo","la":24.46134,"lo":124.14217,"c":"food"},{"n":"Tammy","la":24.32922,"lo":124.08741,"c":"food"},{"n":"Ichack","la":24.46227,"lo":124.13974,"c":"food"},{"n":"Ocean Studio","la":24.46276,"lo":124.13808,"c":"food"},{"n":"フルーツジュエリーファクトリー","la":24.34062,"lo":124.15754,"c":"food"},{"n":"Doteppen 海鮮館どてっぺん","la":24.33333,"lo":124.16508,"c":"food"},{"n":"麒麟閣","la":24.33366,"lo":124.1658,"c":"food"},{"n":"美崎牛本店","la":24.34923,"lo":124.16432,"c":"food"},{"n":"浜","la":24.32548,"lo":124.07758,"c":"food"},{"n":"林","la":24.45084,"lo":124.19611,"c":"food"},{"n":"さびちどうくつ","la":24.52368,"lo":124.2816,"c":"food"},{"n":"ヤシ記念館","la":24.44945,"lo":124.19448,"c":"food"},{"n":"cafe YU-TO","la":24.449,"lo":124.16865,"c":"food"},{"n":"寿五八","la":24.34122,"lo":124.15696,"c":"food"},{"n":"てっぱんあたく","la":24.34091,"lo":124.14875,"c":"food"},{"n":"和風亭","la":24.33738,"lo":124.18309,"c":"food"},{"n":"Cafe Iconoma","la":24.24369,"lo":124.01657,"c":"food"},{"n":"三川食堂","la":24.39174,"lo":124.20722,"c":"food"},{"n":"お食事処珈琲亭","la":24.33686,"lo":124.17138,"c":"food"},{"n":"イーストチャイナシー","la":24.33721,"lo":124.15831,"c":"hotel","ad":"沖縄県石垣市美崎町","w":"https://www.courthotels.co.jp/eastchinasea/"},{"n":"星のや竹富島","la":24.32155,"lo":124.0961,"c":"hotel","ad":"沖縄県八重山郡竹富町竹富","w":"https://hoshinoya.com/taketomijima/"},{"n":"ホテルミヤヒラ","la":24.33836,"lo":124.15557,"c":"hotel","ad":"沖縄県石垣市美崎町","w":"https://www.miyahira.co.jp"},{"n":"東横イン","la":24.33856,"lo":124.14861,"c":"hotel","ad":"沖縄県石垣市浜崎町三丁目","w":"https://www.toyoko-inn.com/index.php/search/detail/00214/"},{"n":"アパホテル","la":24.33518,"lo":124.15926,"c":"hotel","ad":"沖縄県石垣市八島町一丁目","w":"https://www.apahotel.com/hotel/kyushu-okinawa/okinawa/ishigakijima/"},{"n":"ペンションニュー浜乃荘","la":24.34088,"lo":124.14929,"c":"hotel","ad":"沖縄県石垣市浜崎町二丁目","w":"https://hamanoso-hamamarine.okinawa","ht":"guest_house"},{"n":"アートホテル石垣島","la":24.34757,"lo":124.1616,"c":"hotel","w":"https://www.art-ishigakijima.com/"},{"n":"お宿 やまさし","la":24.33999,"lo":124.15535,"c":"hotel","ad":"沖縄県石垣市美崎町","ht":"hostel"},{"n":"上や","la":24.46128,"lo":124.14137,"c":"hotel","w":"jo-ya.jp"},{"n":"るらりや","la":24.46124,"lo":124.141,"c":"hotel","w":"https://www.lulaliya.com/"},{"n":"先島ビジネスホテル","la":24.33401,"lo":124.15972,"c":"hotel","ad":"沖縄県石垣市八島町一丁目","w":"https://primenet2010.biz/sakishima/"},{"n":"ホテルミスター金城サンズイン石垣島","la":24.33252,"lo":124.17545,"c":"hotel","w":"https://hotelmrkinjosunsinishigaki.jphotel.site/"},{"n":"ゲストハウス おり姫","la":24.33457,"lo":124.16012,"c":"hotel","ad":"沖縄県石垣市八島町一丁目","w":"https://www.orihime.tv/guest-house-orihime/","ht":"guest_house"},{"n":"Guest House Yun Terrace","la":24.33488,"lo":124.16405,"c":"hotel","oh":"Mo-Su 15:00-22:00","w":"https://yunterrace.com/","ht":"guest_house"},{"n":"島宿月桃屋","la":24.3399,"lo":124.15009,"c":"hotel","ad":"沖縄県石垣市浜崎町二丁目","w":"https://gettouya.jp/"},{"n":"ベッセルホテル石垣島","la":24.33974,"lo":124.15158,"c":"hotel","ad":"沖縄県石垣市浜崎町一丁目","w":"https://www.vessel-hotel.jp/hotel/ishigaki/"},{"n":"ホテルロイヤルマリンパレス石垣島","la":24.35548,"lo":124.13593,"c":"hotel","ad":"沖縄県石垣市新川","w":"https://www.royalmarinepalace.com"},{"n":"クラブメッド石垣島","la":24.47814,"lo":124.12317,"c":"hotel","ad":"石垣市"},{"n":"ルートイン","la":24.34253,"lo":124.15131,"c":"hotel","ad":"沖縄県石垣市新栄町","w":"https://www.hotel-grantia.co.jp/ishigaki/"},{"n":"まつかぜザゲストハウス","la":24.33733,"lo":124.1691,"c":"hotel","ht":"guest_house"},{"n":"リゾートライフカビラ","la":24.46154,"lo":124.14024,"c":"hotel","ht":"guest_house"},{"n":"カフェロッタ","la":24.45831,"lo":124.13987,"c":"hotel"},{"n":"竹富島そうりゃ","la":24.33182,"lo":124.08512,"c":"hotel","w":"http://www8.plala.or.jp/street/sourya/","ht":"guest_house"},{"n":"ビーチホテルサンシャイン","la":24.35932,"lo":124.12146,"c":"hotel"},{"n":"Oase Maezato","la":24.33559,"lo":124.18521,"c":"hotel","w":"https://oase-villa.com/accommodation/maezato/","ht":"apartment"},{"n":"フサキリゾートビレッジ","la":24.37094,"lo":124.11418,"c":"hotel"},{"n":"ANAインターコンチネンタル石垣リゾート","la":24.33374,"lo":124.18211,"c":"hotel"},{"n":"Genius Resort石垣島川平","la":24.45018,"lo":124.16519,"c":"hotel","ad":"沖縄県石垣市川平"},{"n":"JYH","la":24.32993,"lo":124.08769,"c":"hotel","ht":"hostel"},{"n":"民宿まつや","la":24.33758,"lo":124.15852,"c":"hotel","ht":"hostel"},{"n":"Happy Holiday","la":24.3372,"lo":124.15919,"c":"hotel"},{"n":"Iriwa","la":24.46361,"lo":124.13639,"c":"hotel","ht":"guest_house"},{"n":"味の宿 安らぎ","la":24.45948,"lo":124.13979,"c":"hotel","ht":"guest_house"},{"n":"大浜荘","la":24.46195,"lo":124.14073,"c":"hotel","ht":"guest_house"},{"n":"まりんはうす ＜石垣島＞","la":24.46045,"lo":124.14235,"c":"hotel","ht":"guest_house"},{"n":"かーらB＆B","la":24.45938,"lo":124.14049,"c":"hotel","ht":"guest_house"},{"n":"ホテルピースアイランド竹富島","la":24.33278,"lo":124.08341,"c":"hotel"},{"n":"新田荘","la":24.33065,"lo":124.08402,"c":"hotel","ht":"guest_house"},{"n":"民宿 泉屋","la":24.33131,"lo":124.08488,"c":"hotel","ht":"guest_house"},{"n":"のはら荘","la":24.33093,"lo":124.08337,"c":"hotel","ht":"guest_house"},{"n":"Ho Aloha","la":24.35714,"lo":124.12779,"c":"hotel","ht":"guest_house"},{"n":"古民家の宿ひらた","la":24.33814,"lo":124.16537,"c":"hotel"},{"n":"民宿さくま","la":24.33679,"lo":124.16006,"c":"hotel","ht":"guest_house"},{"n":"炭火燒肉大","la":24.33668,"lo":124.18255,"c":"hotel"},{"n":"Matutake Sou","la":24.33088,"lo":124.08734,"c":"hotel","ht":"guest_house"},{"n":"Ishigaki Sunset Cove Hotel","la":24.48489,"lo":124.22689,"c":"hotel"},{"n":"石垣リゾートグランヴィリオホテル","la":24.3572,"lo":124.12433,"c":"hotel"},{"n":"GranView ISHIGAKI","la":24.33835,"lo":124.15825,"c":"hotel"},{"n":"COCOハウス","la":24.66858,"lo":124.70243,"c":"hotel","ht":"guest_house"},{"n":"ペンションアクアガーデン","la":24.48255,"lo":124.22719,"c":"hotel","ht":"guest_house"},{"n":"民宿しまかぜ","la":24.33298,"lo":124.17601,"c":"hotel","ht":"guest_house"},{"n":"マックスバリュ","la":24.34827,"lo":124.14729,"c":"shop","s":90,"ad":"沖縄県石垣市新栄町","oh":"24/7","w":"https://www.aeon-ryukyu.jp/store/maxvalu/arakawa/"},{"n":"サンキ","la":24.34816,"lo":124.1474,"c":"shop","t":["服飾"],"s":60,"ad":"沖縄県石垣市新栄町","oh":"Mo-Su 10:00-19:00","w":"https://www.fi-sanki.co.jp/shop/detail.php?id=164&pref_id=47&city=&word_search="},{"n":"ファミリーマート","la":24.34236,"lo":124.16646,"c":"shop","j":"ファミリーマート石垣八重高前店","t":["超商"],"s":15,"oh":"24/7","w":"https://www.family.co.jp/"},{"n":"ゆらてぃく市場","la":24.34181,"lo":124.15417,"c":"shop","s":90,"ad":"沖縄県石垣市新栄町","oh":"Mo-Su 09:00-18:00","w":"http://www.yaeyama-pain.com/index.html"},{"n":"ファミリーマート石垣市役所前店","la":24.34255,"lo":124.15452,"c":"shop","t":["超商"],"s":15,"oh":"24/7","w":"https://www.family.co.jp/"},{"n":"海人","la":24.33811,"lo":124.15557,"c":"shop","t":["服飾"],"s":60,"ad":"沖縄県石垣市美崎町","oh":"Mo-Su 09:00-21:00","w":"https://www.uminchu-okinawa.com"},{"n":"ファミリーマート 石垣真栄里バイパス店","la":24.33574,"lo":124.17793,"c":"shop","t":["超商"],"s":15,"oh":"24/7","w":"https://www.family.co.jp/"},{"n":"ファミリーマート石垣新川シード店","la":24.35254,"lo":124.14892,"c":"shop","t":["超商"],"s":15,"oh":"24/7","w":"https://www.family.co.jp/"},{"n":"ファミリーマート石垣平得店","la":24.34093,"lo":124.17547,"c":"shop","t":["超商"],"s":15,"oh":"24/7","w":"https://www.family.co.jp/"},{"n":"3A","la":24.33765,"lo":124.18321,"c":"shop","j":"エディオン","t":["電器"],"s":60},{"n":"ダイソー","la":24.33635,"lo":124.18091,"c":"shop","j":"ダイソーやいま店","t":["激安雜貨"],"s":60,"w":"http://daiso-sangyo.co.jp"},{"n":"ダイソー石垣平真店","la":24.3362,"lo":124.17018,"c":"shop","t":["激安雜貨"],"s":60,"w":"http://daiso-sangyo.co.jp"},{"n":"Puka Shell","la":24.45186,"lo":124.19514,"c":"shop","j":"プカシェル","t":["市場老街"],"s":40,"oh":"11:00-17:00"},{"n":"MaxValu超市","la":24.33611,"lo":124.18125,"c":"shop","j":"マックスバリュ","s":90},{"n":"ドン・キホーテ","la":24.34124,"lo":124.19161,"c":"shop","t":["激安雜貨"],"s":60,"oh":"24/7"},{"n":"マックスバリュー石垣店","la":24.34181,"lo":124.16715,"c":"shop","s":90},{"n":"宮里商店","la":24.45909,"lo":124.14056,"c":"shop","s":90},{"n":"マックスバリュやいま","la":24.33642,"lo":124.18138,"c":"shop","s":90},{"n":"ベーカリーピナコラーダ","la":24.46251,"lo":124.14145,"c":"shop","t":["美食巡禮"],"s":40},{"n":"たま商店","la":24.23918,"lo":124.01575,"c":"shop","s":90},{"n":"石垣島ショッピングプラザ","la":24.33982,"lo":124.1786,"c":"shop","t":["市場老街"],"s":40},{"n":"徳村菓子店","la":24.3344,"lo":124.1768,"c":"shop","t":["美食巡禮"],"s":40},{"n":"SABO","la":24.33883,"lo":124.1578,"c":"shop","t":["服飾"],"s":60},{"n":"新川漁港","la":24.34783,"lo":124.14531,"c":"shop","t":["市場老街"],"s":90},{"n":"石垣市特産品販売センター","la":24.33979,"lo":124.15798,"c":"shop","t":["市場老街"],"s":90},{"n":"さーたー屋","la":24.36604,"lo":124.11322,"c":"shop","t":["美食巡禮"],"s":40},{"n":"石桓公設市場","la":24.33979,"lo":124.15805,"c":"shop","s":90},{"n":"吉野雜貨店","la":24.33989,"lo":124.15646,"c":"shop","t":["超商"],"s":15},{"n":"知念商會","la":24.34581,"lo":124.16655,"c":"shop","j":"知念商会","s":90},{"n":"スタジオマーペー","la":24.46189,"lo":124.14016,"c":"shop","t":["服飾"],"s":60},{"n":"川平観光おみやげ品店","la":24.46111,"lo":124.14256,"c":"shop","t":["市場老街"],"s":40},{"n":"明石共同売店","la":24.54012,"lo":124.30001,"c":"shop","s":90},{"n":"東京靴流通センター石垣島店","la":24.33543,"lo":124.18089,"c":"shop","t":["服飾"],"s":60},{"n":"シャンブル八重山店","la":24.34083,"lo":124.19225,"c":"shop","t":["服飾"],"s":60},{"n":"ファッションセンターしまむら八重山店","la":24.33583,"lo":124.18051,"c":"shop","j":"ファッションセンター しまむら八重山店","t":["服飾"],"s":60},{"n":"ベスト電器登野城店","la":24.33738,"lo":124.1693,"c":"shop","t":["電器"],"s":60},{"n":"アベイル八重山店","la":24.34059,"lo":124.19139,"c":"shop","t":["服飾"],"s":60},{"n":"バースディ八重山店","la":24.34071,"lo":124.1918,"c":"shop","t":["服飾"],"s":60},{"n":"730コート","la":24.33843,"lo":124.15776,"c":"shop","s":90},{"n":"石垣名蔵果樹生産組合(直販所)","la":24.39265,"lo":124.16359,"c":"shop","s":90},{"n":"ハッピーマートほんな","la":24.34204,"lo":124.15853,"c":"shop","s":90},{"n":"イナフク","la":24.33061,"lo":124.08535,"c":"shop","t":["市場老街"],"s":40},{"n":"カイジ浜売店","la":24.3203,"lo":124.07704,"c":"shop","t":["激安雜貨"],"s":60},{"n":"トミーのパン","la":24.4474,"lo":124.17557,"c":"shop","t":["美食巡禮"],"s":40},{"n":"ビックワン石垣店","la":24.33707,"lo":124.16833,"c":"shop","t":["激安雜貨"],"s":60},{"n":"タウンプラザかねひで","la":24.33748,"lo":124.16928,"c":"shop","s":90}]