[{"n":"対馬みうだペンション","la":34.66902,"lo":129.48024,"c":"hotel","w":"https://www.miudapension.info/","ht":"guest_house"},{"n":"ホテルシーサイドアネックス","la":34.20308,"lo":129.29117,"c":"hotel"},{"n":"かいかん食堂","la":34.65557,"lo":129.46627,"c":"food","cu":"japanese"},{"n":"民宿 西泊","la":34.65652,"lo":129.47837,"c":"hotel","ht":"hostel"},{"n":"Hotel Inn","la":34.2757,"lo":129.32166,"c":"hotel","j":"Hotel 空港Inn"},{"n":"Guesthouse","la":34.28044,"lo":129.32554,"c":"hotel"},{"n":"Sakana-ya","la":34.27827,"lo":129.3244,"c":"food","cu":"izakaya"},{"n":"Tsushima Grand Hotel","la":34.25841,"lo":129.32253,"c":"hotel"},{"n":"Kayak Centre Club Rooms","la":34.29366,"lo":129.26247,"c":"hotel","ht":"guest_house"},{"n":"しげちゃんラーメン","la":34.25183,"lo":129.31433,"c":"food","cu":"ramen"},{"n":"Bamboo","la":34.20267,"lo":129.29143,"c":"food","cu":"japanese"},{"n":"千両","la":34.20312,"lo":129.29158,"c":"food","cu":"japanese;_italian;_chinese"},{"n":"東横イン対馬厳原","la":34.20425,"lo":129.28982,"c":"hotel","j":"東横イン","ad":"長崎県対馬市厳原町今屋敷","w":"toyoko-inn.com"},{"n":"いけす料理 志まもと","la":34.20258,"lo":129.28856,"c":"food","cu":"japanese","w":"tsushima-shimamoto.jp"},{"n":"Crepe House","la":34.18816,"lo":129.27822,"c":"food","cu":"crepe"},{"n":"おはしのくに","la":34.20998,"lo":129.29007,"c":"food","cu":"Izakaya"},{"n":"創菜もぐもぐ","la":34.21001,"lo":129.2902,"c":"food","cu":"bento"},{"n":"花海荘 ＜対馬＞","la":34.65539,"lo":129.4826,"c":"hotel","w":"https://kamiso-tsushima.com/"},{"n":"みなと寿司","la":34.65488,"lo":129.46515,"c":"food","cu":"japanese;sushi"},{"n":"梅屋ホテル","la":34.65468,"lo":129.46523,"c":"hotel","w":"https://www.tsushima-net.org/"},{"n":"ホテル柿谷","la":34.20458,"lo":129.28936,"c":"hotel","w":"https://www.tsushima-net.org/"},{"n":"丸屋ホテル","la":34.20191,"lo":129.28787,"c":"hotel","w":"https://www.tsushima-net.org/"}]