[{"n":"旧下ヨイチ運上家","la":43.19784,"lo":140.78815,"c":"spot","s":60,"wt":"旧下ヨイチ運上家","w":"https://www.town.yoichi.hokkaido.jp/machi/syoukai/yoichiunzyouya.html"},{"n":"法勝寺","la":43.10015,"lo":140.4637,"c":"spot","t":["神社寺廟"],"s":30,"ad":"北海道泊村盃村寺町","w":"https://www.sotozen-net.or.jp/"},{"n":"神威岬","la":43.3335,"lo":140.34676,"c":"spot","t":["自然風景","夜景展望"],"s":40,"w":"https://en.japantravel.com/hokkaido/cape-kamui-shakotan-peninsula/2758"},{"n":"小樽運河","la":43.20473,"lo":140.99943,"c":"spot","s":60,"ad":"北海道小樽市港町","w":"https://otaru.gr.jp/shop/otarucanal"},{"n":"末日聖徒イエス•キリスト教会","la":43.1941,"lo":140.99375,"c":"spot","t":["神社寺廟"],"s":30,"w":"https://www.ldschurch.jp/"},{"n":"天狗山","la":43.16841,"lo":140.96981,"c":"spot","t":["自然風景","夜景展望"],"s":60,"wt":"天狗山_(小樽市)"},{"n":"みやこ公園","la":43.04845,"lo":140.83342,"c":"spot","t":["自然風景"],"s":45,"w":"https://www.akaigawa.com/shisetsu/shoukouen/post_15.html"},{"n":"旧余市福原漁場","la":43.20002,"lo":140.77888,"c":"spot","s":60,"w":"https://www.town.yoichi.hokkaido.jp/machi/syoukai/fukuharagyoba.html"},{"n":"茂入神社","la":43.19753,"lo":140.78803,"c":"spot","t":["神社寺廟"],"s":30,"ad":"北海道余市町入舟町"},{"n":"nikka whisky 工廠","la":43.18643,"lo":140.79136,"c":"spot","j":"ニッカウヰスキー余市蒸留所","s":60},{"n":"舊日本郵船株式會社小樽支店","la":43.2071,"lo":140.9985,"c":"spot","j":"旧日本郵船株式会社小樽支店","t":["博物館藝術"],"s":90},{"n":"ふるびら温泉 しおかぜ","la":43.28333,"lo":140.63638,"c":"spot","t":["溫泉"],"s":90,"ad":"北海道古平町新地町","w":"https://www.town.furubira.lg.jp/tourism/detail.php?id=68"},{"n":"Yoichi Distillery Nikka whisky 工廠","la":43.18735,"lo":140.79156,"c":"spot","j":"Yoichi Distillery Nikka Whisky","t":["美酒微醺"],"s":60,"w":"http://www.nikka.com/eng/distilleries/yoichi/index.html"},{"n":"余市宇宙記念館「スペース童夢」","la":43.18903,"lo":140.78879,"c":"spot","t":["博物館藝術"],"s":90,"oh":"Tu-Su 09:00-17:00","w":"http://www.spacedome.jp/"},{"n":"茂岩温泉","la":43.11327,"lo":140.45272,"c":"spot","t":["溫泉"],"s":90,"ad":"北海道泊村興志内村茂岩","w":"https://www.vill.tomari.hokkaido.jp/kankou/hotel/3938.html"},{"n":"原子力PRセンターとまりん館","la":43.03174,"lo":140.53231,"c":"spot","t":["博物館藝術"],"s":90,"ad":"北海道泊村堀株村古川","w":"https://www.hepco.co.jp/corporate/nextgeneration/tomarin/index.html"},{"n":"渋井神社","la":43.04401,"lo":140.50677,"c":"spot","t":["神社寺廟"],"s":30,"ad":"北海道泊村堀株村渋井"},{"n":"塩谷丸山","la":43.17895,"lo":140.92243,"c":"spot","t":["自然風景","夜景展望"],"s":60},{"n":"島武意海岸","la":43.3731,"lo":140.47745,"c":"spot","t":["自然風景","親子同樂"],"s":90,"oh":"24/7"},{"n":"積丹岬","la":43.3722,"lo":140.46222,"c":"spot","s":60},{"n":"余別岳","la":43.26007,"lo":140.45914,"c":"spot","t":["自然風景","夜景展望"],"s":60},{"n":"мастерская стекла","la":43.16829,"lo":140.99254,"c":"spot","t":["博物館藝術"],"s":90},{"n":"さくらんぼ山観光農園","la":43.13583,"lo":140.77166,"c":"spot","s":60},{"n":"えびす岩","la":43.23669,"lo":140.73502,"c":"spot","s":60},{"n":"蘭島海水浴場","la":43.19906,"lo":140.85175,"c":"spot","t":["自然風景","夜景展望"],"s":40},{"n":"積丹岳","la":43.27062,"lo":140.48034,"c":"spot","t":["自然風景","夜景展望"],"s":60},{"n":"北海道鐵道發祥之地","la":43.20942,"lo":140.99844,"c":"spot","s":60},{"n":"キロロリゾート","la":43.06736,"lo":140.99035,"c":"spot","s":60},{"n":"於古発山","la":43.15653,"lo":140.93434,"c":"spot","t":["自然風景","夜景展望"],"s":60},{"n":"下赤岩山","la":43.23656,"lo":140.99735,"c":"spot","t":["自然風景","夜景展望"],"s":60},{"n":"赤岩山","la":43.23232,"lo":140.982,"c":"spot","t":["自然風景","夜景展望"],"s":60},{"n":"樺山","la":43.21526,"lo":140.92908,"c":"spot","t":["自然風景","夜景展望"],"s":60},{"n":"船取山","la":43.18968,"lo":140.87291,"c":"spot","t":["自然風景","夜景展望"],"s":60},{"n":"毛無山","la":43.15971,"lo":140.90673,"c":"spot","t":["自然風景","夜景展望"],"s":60},{"n":"金吾龍神社","la":43.19693,"lo":140.84718,"c":"spot","t":["神社寺廟"],"s":30,"wt":"金吾龍神社"},{"n":"ポンネアンチシ山","la":43.24773,"lo":140.46591,"c":"spot","t":["自然風景","夜景展望"],"s":60},{"n":"珊内岳","la":43.23397,"lo":140.41178,"c":"spot","t":["自然風景","夜景展望"],"s":60},{"n":"鉞山","la":43.22693,"lo":140.37405,"c":"spot","t":["自然風景","夜景展望"],"s":60},{"n":"屛風山","la":43.21363,"lo":140.42369,"c":"spot","t":["自然風景","夜景展望"],"s":60},{"n":"当丸山","la":43.19715,"lo":140.53697,"c":"spot","t":["自然風景","夜景展望"],"s":60},{"n":"滝ノ沢山","la":43.14316,"lo":140.51021,"c":"spot","t":["自然風景","夜景展望"],"s":60},{"n":"大天狗山","la":43.25037,"lo":140.36688,"c":"spot","t":["自然風景","夜景展望"],"s":60},{"n":"摺鉢山","la":43.25645,"lo":140.61373,"c":"spot","t":["自然風景","夜景展望"],"s":60},{"n":"稲穂嶺","la":43.03467,"lo":140.70031,"c":"spot","t":["自然風景","夜景展望"],"s":60},{"n":"銀山","la":43.01607,"lo":140.72906,"c":"spot","t":["自然風景","夜景展望"],"s":60},{"n":"禅源寺","la":43.26355,"lo":140.6367,"c":"spot","t":["神社寺廟"],"s":30,"ad":"北海道古平町浜町"},{"n":"阿女鱒岳","la":43.03908,"lo":140.93823,"c":"spot","t":["自然風景","夜景展望"],"s":60},{"n":"大登山","la":43.12462,"lo":140.88093,"c":"spot","t":["自然風景","夜景展望"],"s":60},{"n":"元服山","la":43.11421,"lo":140.83276,"c":"spot","t":["自然風景","夜景展望"],"s":60},{"n":"能蘭山","la":43.21393,"lo":140.3463,"c":"spot","t":["自然風景","夜景展望"],"s":60},{"n":"両古美山","la":43.21386,"lo":140.52629,"c":"spot","t":["自然風景","夜景展望"],"s":60},{"n":"泥ノ木山","la":43.23046,"lo":140.53444,"c":"spot","t":["自然風景","夜景展望"],"s":60},{"n":"小登山","la":43.12595,"lo":140.85972,"c":"spot","t":["自然風景","夜景展望"],"s":60},{"n":"運河公園","la":43.2077,"lo":140.99875,"c":"spot","t":["自然風景"],"s":45},{"n":"蝋燭岩","la":43.25295,"lo":140.72327,"c":"spot","s":60,"wt":"ローソク岩"},{"n":"岬の湯;しゃこたん","la":43.33859,"lo":140.45439,"c":"spot","t":["溫泉"],"s":90},{"n":"花園公園","la":43.18915,"lo":140.99936,"c":"spot","t":["自然風景"],"s":45},{"n":"マスジド・アル・ヌール小樽","la":43.20413,"lo":140.9972,"c":"spot","t":["神社寺廟"],"s":30},{"n":"創価学会","la":43.21035,"lo":140.76158,"c":"spot","t":["神社寺廟"],"s":30,"ad":"北海道余市町"},{"n":"カルデラ公園","la":43.08475,"lo":140.81133,"c":"spot","t":["自然風景"],"s":45,"w":"https://www.akaigawa.com/shisetsu/shoukouen/post_16.html"},{"n":"電磁台","la":43.33006,"lo":140.35467,"c":"spot","t":["自然風景","夜景展望"],"s":40},{"n":"展望台","la":43.33012,"lo":140.35791,"c":"spot","t":["自然風景","夜景展望"],"s":40},{"n":"積丹岬灯台展望台","la":43.37333,"lo":140.48202,"c":"spot","t":["自然風景","夜景展望"],"s":40},{"n":"旭展望台","la":43.197,"lo":140.98462,"c":"spot","t":["自然風景","夜景展望"],"s":40},{"n":"潮祭り","la":43.19858,"lo":140.99614,"c":"spot","t":["博物館藝術"],"s":30},{"n":"島武意海岸展望台","la":43.37215,"lo":140.47774,"c":"spot","t":["自然風景","夜景展望"],"s":40},{"n":"あんない展望公園","la":43.24233,"lo":140.33265,"c":"spot","t":["自然風景","夜景展望"],"s":40},{"n":"蘭島 キリスト教会","la":43.19853,"lo":140.86363,"c":"spot","t":["神社寺廟"],"s":30},{"n":"恵比須神社","la":43.26493,"lo":140.63918,"c":"spot","t":["神社寺廟"],"s":30},{"n":"天狗岳","la":43.18483,"lo":140.66087,"c":"spot","t":["自然風景","夜景展望"],"s":60},{"n":"小樽公園こどもの国","la":43.18717,"lo":140.99401,"c":"spot","t":["主題樂園","親子同樂"],"s":300},{"n":"ED75 501","la":43.21034,"lo":140.99903,"c":"spot","t":["歷史古蹟"],"s":45},{"n":"キハ22 56","la":43.21019,"lo":140.99893,"c":"spot","t":["歷史古蹟"],"s":45},{"n":"豊浜トンネル","la":43.25304,"lo":140.68802,"c":"spot","s":60},{"n":"出岬灯台","la":43.37321,"lo":140.48143,"c":"spot","s":60},{"n":"神威岩","la":43.33571,"lo":140.3428,"c":"spot","s":60},{"n":"女郎子岩","la":43.37073,"lo":140.50054,"c":"spot","s":60},{"n":"西の河原","la":43.26067,"lo":140.33113,"c":"spot","s":60},{"n":"セタカムイ岩","la":43.25549,"lo":140.68718,"c":"spot","s":60},{"n":"黄金岬","la":43.30317,"lo":140.60135,"c":"spot","s":60},{"n":"桃岩","la":43.21146,"lo":140.89492,"c":"spot","s":60},{"n":"宝島","la":43.30727,"lo":140.60176,"c":"spot","s":60},{"n":"余市港","la":43.21196,"lo":140.77617,"c":"spot","s":60},{"n":"よいち水産博物館","la":43.19665,"lo":140.78681,"c":"spot","t":["博物館藝術"],"s":90},{"n":"1号貯蔵庫","la":43.18537,"lo":140.79055,"c":"spot","s":60},{"n":"青の洞窟","la":43.22624,"lo":140.92713,"c":"spot","s":60},{"n":"美国港","la":43.30089,"lo":140.60286,"c":"spot","s":60},{"n":"ビヤノ岬","la":43.3087,"lo":140.59085,"c":"spot","s":60},{"n":"旧安田銀行","la":43.19968,"lo":140.99958,"c":"spot","s":60},{"n":"水中展望船","la":43.29873,"lo":140.60311,"c":"spot","s":60},{"n":"ニッカ会館","la":43.18532,"lo":140.78924,"c":"spot","s":60},{"n":"余市湾","la":43.19903,"lo":140.79708,"c":"spot","s":60},{"n":"旧事務所","la":43.18677,"lo":140.79077,"c":"spot","s":60},{"n":"乾燥棟（キルン塔）","la":43.18733,"lo":140.79149,"c":"spot","s":60},{"n":"正門","la":43.18728,"lo":140.79186,"c":"spot","s":60},{"n":"蒸溜棟","la":43.18696,"lo":140.79132,"c":"spot","s":60},{"n":"リタハウス","la":43.18649,"lo":140.79089,"c":"spot","s":60},{"n":"旧竹鶴邸","la":43.1858,"lo":140.79065,"c":"spot","s":60},{"n":"醗酵棟","la":43.18702,"lo":140.79047,"c":"spot","s":60},{"n":"滝ﾉ澗ﾉ岬","la":43.25019,"lo":140.71786,"c":"spot","s":60},{"n":"ﾔﾏｼﾒ番屋","la":43.29735,"lo":140.60116,"c":"spot","s":60},{"n":"蛸穴ﾉ岬","la":43.25258,"lo":140.70844,"c":"spot","s":60},{"n":"ﾓｲﾚ山","la":43.19525,"lo":140.78937,"c":"spot","s":60},{"n":"旧大家倉庫","la":43.20175,"lo":140.99988,"c":"spot","s":60},{"n":"群来町","la":43.29179,"lo":140.63212,"c":"spot","s":60},{"n":"新地十字街","la":43.27738,"lo":140.6386,"c":"spot","s":60},{"n":"余市町斎場","la":43.21898,"lo":140.74044,"c":"spot","s":60},{"n":"豊浜トンネル崩落事故慰霊碑","la":43.2541,"lo":140.68491,"c":"spot","t":["歷史古蹟"],"s":45},{"n":"大川町3丁目","la":43.1926,"lo":140.7941,"c":"spot","s":60},{"n":"丸山","la":43.28507,"lo":140.64075,"c":"spot","t":["自然風景","夜景展望"],"s":60},{"n":"金光教","la":43.19026,"lo":140.99969,"c":"spot","t":["神社寺廟"],"s":30},{"n":"赤井川カルデラ温泉;保養センター","la":43.08119,"lo":140.81231,"c":"spot","t":["溫泉"],"s":90},{"n":"伊藤長右衛門像","la":43.18678,"lo":140.9944,"c":"spot","t":["博物館藝術"],"s":30},{"n":"石川啄木歌碑","la":43.19828,"lo":140.99379,"c":"spot","t":["歷史古蹟"],"s":45},{"n":"地鎮山環状列石","la":43.19738,"lo":140.87131,"c":"spot","t":["歷史古蹟"],"s":45},{"n":"忍路環状列石","la":43.19963,"lo":140.87494,"c":"spot","t":["歷史古蹟"],"s":45},{"n":"西崎山環状列石","la":43.19043,"lo":140.84651,"c":"spot","t":["歷史古蹟"],"s":45},{"n":"あらはばき神社 ( 奥宮 )","la":43.19727,"lo":140.84653,"c":"spot","t":["神社寺廟"],"s":30},{"n":"フゴッペ洞窟","la":43.19465,"lo":140.83876,"c":"spot","t":["歷史古蹟"],"s":45},{"n":"冷水峠 カルデラ展望所","la":43.11772,"lo":140.82083,"c":"spot","t":["自然風景","夜景展望"],"s":40},{"n":"女郎子岩展望台","la":43.36961,"lo":140.49837,"c":"spot","t":["自然風景","夜景展望"],"s":40},{"n":"熊追山","la":43.12282,"lo":140.54698,"c":"spot","t":["自然風景","夜景展望"],"s":60},{"n":"大森山","la":43.28345,"lo":140.61849,"c":"spot","t":["自然風景","夜景展望"],"s":60},{"n":"稲倉石山","la":43.15751,"lo":140.64597,"c":"spot","t":["自然風景","夜景展望"],"s":60},{"n":"八内岳","la":43.07816,"lo":140.63127,"c":"spot","t":["自然風景","夜景展望"],"s":60},{"n":"三角山","la":43.06527,"lo":140.58185,"c":"spot","t":["自然風景","夜景展望"],"s":60},{"n":"木無山","la":43.05905,"lo":140.62302,"c":"spot","t":["自然風景","夜景展望"],"s":60},{"n":"二ッ森","la":43.0051,"lo":140.81341,"c":"spot","t":["自然風景","夜景展望"],"s":60},{"n":"浜中・モイレ海水浴場","la":43.19868,"lo":140.78549,"c":"spot","t":["自然風景","親子同樂"],"s":90},{"n":"天理教　余市港分教会","la":43.18376,"lo":140.79115,"c":"spot","t":["神社寺廟"],"s":30},{"n":"誓願寺","la":43.23199,"lo":140.99878,"c":"spot","t":["神社寺廟"],"s":30},{"n":"伊藤長右衛門","la":43.20748,"lo":140.99905,"c":"spot","t":["歷史古蹟"],"s":45},{"n":"斎藤吉郎","la":43.20505,"lo":140.99949,"c":"spot","t":["歷史古蹟"],"s":45},{"n":"厳島神社","la":43.14417,"lo":140.43047,"c":"spot","t":["神社寺廟"],"s":30},{"n":"浄国寺","la":43.141,"lo":140.43363,"c":"spot","t":["神社寺廟"],"s":30},{"n":"松倉岩","la":43.12688,"lo":140.96191,"c":"spot","t":["自然風景","夜景展望"],"s":60},{"n":"北丸山","la":43.10101,"lo":140.81072,"c":"spot","t":["自然風景","夜景展望"],"s":60},{"n":"大黒山","la":43.10571,"lo":140.77615,"c":"spot","t":["自然風景","夜景展望"],"s":60},{"n":"DD16 17","la":43.21122,"lo":140.99997,"c":"spot","t":["歷史古蹟"],"s":45},{"n":"DE10 503","la":43.21016,"lo":140.99965,"c":"spot","t":["歷史古蹟"],"s":45},{"n":"C12 6","la":43.20983,"lo":140.99874,"c":"spot","t":["歷史古蹟"],"s":45},{"n":"ホキ2226","la":43.21041,"lo":141.0,"c":"spot","t":["歷史古蹟"],"s":45},{"n":"トラ57964","la":43.21034,"lo":140.9999,"c":"spot","t":["歷史古蹟"],"s":45},{"n":"セキ7342","la":43.21029,"lo":140.99983,"c":"spot","t":["歷史古蹟"],"s":45},{"n":"ワム82506","la":43.21023,"lo":140.99975,"c":"spot","t":["歷史古蹟"],"s":45},{"n":"キシ80 12","la":43.21,"lo":140.99883,"c":"spot","t":["歷史古蹟"],"s":45},{"n":"キハユニ25 1","la":43.2105,"lo":140.99916,"c":"spot","t":["歷史古蹟"],"s":45},{"n":"キハ27 11","la":43.21065,"lo":140.9993,"c":"spot","t":["歷史古蹟"],"s":45},{"n":"キロ26 107","la":43.2108,"lo":140.99943,"c":"spot","t":["歷史古蹟"],"s":45},{"n":"キハ56 23","la":43.21096,"lo":140.99961,"c":"spot","t":["歷史古蹟"],"s":45},{"n":"龍宮神社","la":43.20045,"lo":140.99224,"c":"spot","t":["神社寺廟"],"s":30},{"n":"小林多喜二文学碑","la":43.19675,"lo":140.98178,"c":"spot","t":["博物館藝術"],"s":30},{"n":"からまつ公園","la":43.18443,"lo":140.97148,"c":"spot","t":["自然風景"],"s":45},{"n":"入船公園","la":43.18241,"lo":140.99165,"c":"spot","t":["自然風景"],"s":45},{"n":"最上公園","la":43.17846,"lo":140.97762,"c":"spot","t":["自然風景"],"s":45},{"n":"長橋なえぼ公園","la":43.21008,"lo":140.97784,"c":"spot","t":["自然風景"],"s":45},{"n":"ウイスキー博物館","la":43.18555,"lo":140.7901,"c":"spot","t":["博物館藝術"],"s":90},{"n":"花壇","la":43.04882,"lo":140.83478,"c":"spot","t":["自然風景"],"s":45},{"n":"赤岩稲荷神社","la":43.22327,"lo":140.99584,"c":"spot","t":["神社寺廟"],"s":30},{"n":"旧右近倉庫","la":43.20819,"lo":140.99954,"c":"spot","t":["歷史古蹟"],"s":45},{"n":"旧増田倉庫","la":43.20796,"lo":140.99949,"c":"spot","t":["歷史古蹟"],"s":45},{"n":"小樽公園","la":43.19004,"lo":140.99312,"c":"spot","t":["自然風景"],"s":45},{"n":"睦公園","la":43.19096,"lo":140.7938,"c":"spot","t":["自然風景"],"s":45},{"n":"長福寺","la":43.09926,"lo":140.46637,"c":"spot","t":["神社寺廟"],"s":30},{"n":"光徳寺","la":43.09997,"lo":140.46284,"c":"spot","t":["神社寺廟"],"s":30},{"n":"PRESS CAFE","la":43.2049,"lo":140.99923,"c":"spot","t":["歷史古蹟"],"s":45},{"n":"GOLD STONE","la":43.20476,"lo":140.99913,"c":"spot","t":["歷史古蹟"],"s":45},{"n":"GOLD STONE CAFE","la":43.20475,"lo":140.99921,"c":"spot","t":["歷史古蹟"],"s":45},{"n":"浄応寺","la":43.20714,"lo":140.9927,"c":"spot","t":["神社寺廟"],"s":30},{"n":"末広公園","la":43.2145,"lo":140.99737,"c":"spot","t":["自然風景"],"s":45},{"n":"みどり公園","la":43.1908,"lo":140.98519,"c":"spot","t":["自然風景"],"s":45},{"n":"ふれあい遊トピア公園","la":43.11741,"lo":140.73004,"c":"spot","t":["自然風景"],"s":45},{"n":"サンスポーツランドにき","la":43.11568,"lo":140.7323,"c":"spot","t":["自然風景"],"s":45},{"n":"日正寺","la":43.2031,"lo":140.98742,"c":"spot","t":["神社寺廟"],"s":30},{"n":"オタモイ神社","la":43.21534,"lo":140.95955,"c":"spot","t":["神社寺廟"],"s":30},{"n":"珊内ぬくもり温泉","la":43.19686,"lo":140.34823,"c":"spot","t":["溫泉"],"s":90},{"n":"余市川温泉 宇宙の湯","la":43.19247,"lo":140.78592,"c":"spot","t":["溫泉"],"s":90},{"n":"よいち観光温泉","la":43.18572,"lo":140.78283,"c":"spot","t":["溫泉"],"s":90},{"n":"農村公園フルーツパークにき","la":43.15025,"lo":140.79066,"c":"spot","t":["自然風景"],"s":45},{"n":"無漏山不動院","la":43.17621,"lo":140.9996,"c":"spot","t":["神社寺廟"],"s":30},{"n":"赤井川神社","la":43.08647,"lo":140.814,"c":"spot","t":["神社寺廟"],"s":30},{"n":"赤井川村郷土資料館","la":43.08487,"lo":140.82089,"c":"spot","t":["博物館藝術"],"s":90},{"n":"一乗寺","la":43.0998,"lo":140.46555,"c":"spot","t":["神社寺廟"],"s":30},{"n":"教照寺","la":43.32339,"lo":140.37849,"c":"spot","t":["神社寺廟"],"s":30},{"n":"寶海寺","la":43.26696,"lo":140.63591,"c":"spot","t":["神社寺廟"],"s":30},{"n":"恵美須神社","la":43.26491,"lo":140.6391,"c":"spot","t":["神社寺廟"],"s":30},{"n":"正隆寺","la":43.26295,"lo":140.63749,"c":"spot","t":["神社寺廟"],"s":30},{"n":"願雄寺","la":43.26297,"lo":140.63845,"c":"spot","t":["神社寺廟"],"s":30},{"n":"あけぼの公園","la":43.26201,"lo":140.64177,"c":"spot","t":["自然風景"],"s":45},{"n":"さわえ公園","la":43.26082,"lo":140.64744,"c":"spot","t":["自然風景"],"s":45},{"n":"まるやま公園","la":43.28104,"lo":140.64207,"c":"spot","t":["自然風景"],"s":45},{"n":"無量壽寺","la":43.15581,"lo":140.76669,"c":"spot","t":["神社寺廟"],"s":30},{"n":"仁玄寺","la":43.14667,"lo":140.75912,"c":"spot","t":["神社寺廟"],"s":30},{"n":"仁木神社","la":43.14613,"lo":140.77478,"c":"spot","t":["神社寺廟"],"s":30},{"n":"然別神社","la":43.12421,"lo":140.73324,"c":"spot","t":["神社寺廟"],"s":30},{"n":"光明寺","la":43.09202,"lo":140.72215,"c":"spot","t":["神社寺廟"],"s":30},{"n":"大江神社","la":43.09091,"lo":140.72064,"c":"spot","t":["神社寺廟"],"s":30},{"n":"女代神社","la":43.04446,"lo":140.71907,"c":"spot","t":["神社寺廟"],"s":30},{"n":"浄宣寺","la":43.03616,"lo":140.73862,"c":"spot","t":["神社寺廟"],"s":30},{"n":"孝徳寺","la":43.03539,"lo":140.74207,"c":"spot","t":["神社寺廟"],"s":30},{"n":"専念寺","la":43.03115,"lo":140.57767,"c":"spot","t":["神社寺廟"],"s":30},{"n":"聖賢寺","la":43.03579,"lo":140.5616,"c":"spot","t":["神社寺廟"],"s":30},{"n":"大乗寺","la":43.19419,"lo":140.78615,"c":"spot","t":["神社寺廟"],"s":30},{"n":"龍神社","la":43.03419,"lo":140.5288,"c":"spot","t":["神社寺廟"],"s":30},{"n":"大雄寺","la":43.03466,"lo":140.52655,"c":"spot","t":["神社寺廟"],"s":30},{"n":"堀株稲荷神社","la":43.03224,"lo":140.52251,"c":"spot","t":["神社寺廟"],"s":30},{"n":"鶴亀温泉","la":43.193,"lo":140.82181,"c":"spot","t":["溫泉"],"s":90},{"n":"出羽三山神社","la":43.22981,"lo":140.96495,"c":"spot","t":["神社寺廟"],"s":30},{"n":"報恩寺","la":43.19445,"lo":140.78823,"c":"spot","t":["神社寺廟"],"s":30},{"n":"茂入山阿弥陀院","la":43.1945,"lo":140.78738,"c":"spot","t":["神社寺廟"],"s":30},{"n":"明治神社","la":43.1953,"lo":140.78783,"c":"spot","t":["神社寺廟"],"s":30},{"n":"海浜公園３","la":43.19785,"lo":140.78501,"c":"spot","t":["自然風景"],"s":45},{"n":"ヌッチ公園","la":43.19564,"lo":140.76928,"c":"spot","t":["自然風景"],"s":45},{"n":"出雲神社","la":43.19694,"lo":140.76743,"c":"spot","t":["神社寺廟"],"s":30},{"n":"妙圓山法華寺","la":43.19782,"lo":140.76877,"c":"spot","t":["神社寺廟"],"s":30},{"n":"宝隆寺","la":43.19888,"lo":140.76856,"c":"spot","t":["神社寺廟"],"s":30},{"n":"龍護山永全寺","la":43.20127,"lo":140.76719,"c":"spot","t":["神社寺廟"],"s":30},{"n":"法雲山乗念寺","la":43.20463,"lo":140.76714,"c":"spot","t":["神社寺廟"],"s":30},{"n":"余市神社","la":43.21479,"lo":140.77123,"c":"spot","t":["神社寺廟"],"s":30},{"n":"即信寺支院","la":43.19156,"lo":140.7951,"c":"spot","t":["神社寺廟"],"s":30},{"n":"天理教　北余市分教会","la":43.1914,"lo":140.79454,"c":"spot","t":["神社寺廟"],"s":30},{"n":"おおかわ３丁目公園","la":43.19017,"lo":140.80836,"c":"spot","t":["自然風景"],"s":45},{"n":"大川チビッコ公園","la":43.19026,"lo":140.81156,"c":"spot","t":["自然風景"],"s":45},{"n":"ふじ公園","la":43.1867,"lo":140.81033,"c":"spot","t":["自然風景"],"s":45},{"n":"共栄ふれあい公園","la":43.18857,"lo":140.80849,"c":"spot","t":["自然風景"],"s":45},{"n":"すずかけ公園","la":43.18603,"lo":140.80406,"c":"spot","t":["自然風景"],"s":45},{"n":"黒川はまなす公園","la":43.18509,"lo":140.80977,"c":"spot","t":["自然風景"],"s":45},{"n":"黒川八幡神社","la":43.18326,"lo":140.80679,"c":"spot","t":["神社寺廟"],"s":30},{"n":"黒川八幡公園","la":43.18319,"lo":140.80676,"c":"spot","t":["自然風景"],"s":45},{"n":"いなほ公園","la":43.18447,"lo":140.80322,"c":"spot","t":["自然風景"],"s":45},{"n":"誠諦寺","la":43.18794,"lo":140.79844,"c":"spot","t":["神社寺廟"],"s":30},{"n":"余市念法寺","la":43.18598,"lo":140.79624,"c":"spot","t":["神社寺廟"],"s":30},{"n":"川白稲荷神社","la":43.22003,"lo":140.32824,"c":"spot","t":["神社寺廟"],"s":30},{"n":"恵比須３神社","la":43.05706,"lo":140.50062,"c":"spot","t":["神社寺廟"],"s":30},{"n":"智龍寺","la":43.06125,"lo":140.49707,"c":"spot","t":["神社寺廟"],"s":30},{"n":"泊稲荷神社","la":43.06815,"lo":140.49156,"c":"spot","t":["神社寺廟"],"s":30},{"n":"瑞龍山法輪寺","la":43.06842,"lo":140.49446,"c":"spot","t":["神社寺廟"],"s":30},{"n":"前浜海水浴場","la":43.14038,"lo":140.43071,"c":"spot","t":["自然風景","親子同樂"],"s":90},{"n":"オタモイ地蔵尊","la":43.2275,"lo":140.95263,"c":"spot","t":["神社寺廟"],"s":30},{"n":"天龍寺","la":43.13991,"lo":140.4325,"c":"spot","t":["神社寺廟"],"s":30},{"n":"円山公園","la":43.19924,"lo":140.76722,"c":"spot","t":["自然風景"],"s":45},{"n":"リフォレ積丹ユースホステル","la":43.31588,"lo":140.54037,"c":"hotel","w":"http://refore.eco.coocan.jp/youkoso_ji_dan_ban_daohe/Welcome.html","ht":"hostel"},{"n":"アールジェイホテルズオタル","la":43.20433,"lo":140.99567,"c":"hotel","ad":"北海道小樽市稲穂5丁目","w":"https://rjhotels.co.jp/","ht":"motel"},{"n":"旅人・宿B&B いちえ","la":43.21878,"lo":140.99464,"c":"hotel","ad":"北海道小樽市赤岩1丁目","w":"http://www.ryokuyo.com/ichie/","ht":"guest_house"},{"n":"鱗晃荘","la":43.36745,"lo":140.47478,"c":"hotel","w":"https://rinkousou.net/"},{"n":"盃温泉ホテル 潮香荘","la":43.1081,"lo":140.45391,"c":"hotel","w":"https://primenet2010.biz/choukasou/"},{"n":"ｅｍｉｎａ　ｂａｃｋｐａｃｋｅｒｓ","la":43.18541,"lo":140.98714,"c":"hotel","w":"https://otaru-emina.jimdo.com/","ht":"guest_house"},{"n":"ドーミーイン小樽","la":43.19828,"lo":140.99486,"c":"hotel"},{"n":"みはらし","la":43.29434,"lo":140.62406,"c":"hotel","j":"みはらし莊"},{"n":"小樽ヴィラマウンテング","la":43.17858,"lo":140.97691,"c":"hotel","ht":"guest_house"},{"n":"ほり旅館","la":43.27392,"lo":140.63556,"c":"hotel"},{"n":"シェラトン 北海道 キロロリゾート","la":43.06741,"lo":140.98903,"c":"hotel"},{"n":"小樽グリーンホテル本館","la":43.19895,"lo":140.9965,"c":"hotel"},{"n":"エーヴランド ホテル","la":43.13553,"lo":140.82353,"c":"hotel","w":"https://a-brand.jp/?page_id=43"},{"n":"中央旅館","la":43.26579,"lo":140.63881,"c":"hotel"},{"n":"美国観光","la":43.29905,"lo":140.59944,"c":"hotel","j":"美国観光ﾊｳｽ"},{"n":"otaru green hotel","la":43.1994,"lo":140.99755,"c":"hotel"},{"n":"きのえ荘","la":43.13843,"lo":140.43044,"c":"hotel"},{"n":"The Stay Yuki","la":43.20166,"lo":140.99574,"c":"hotel","ht":"apartment"},{"n":"小樽グリーンホテル別館","la":43.19876,"lo":140.99692,"c":"hotel"},{"n":"オーセントホテル小樽","la":43.19596,"lo":140.998,"c":"hotel"},{"n":"さくらガーデン","la":43.20205,"lo":140.85745,"c":"hotel","ht":"guest_house"},{"n":"ビジネスホテル大幸","la":43.1978,"lo":140.99942,"c":"hotel"},{"n":"新倉屋 本店","la":43.19356,"lo":140.9992,"c":"shop","t":["美食巡禮"],"s":40,"ad":"花園1丁目","cu":"japanese","oh":"Mo-Su 09:30-18:00","w":"https://www.niikuraya.com/store/#hanazono"},{"n":"コープさっぽろ","la":43.19394,"lo":140.99212,"c":"shop","s":90,"ad":"北海道小樽市富岡1丁目","oh":"09:00-22:00"},{"n":"イオン","la":43.18521,"lo":140.79902,"c":"shop","s":90,"ad":"北海道余市町黒川町12丁目"},{"n":"サンジェルマン","la":43.19791,"lo":140.99368,"c":"shop","t":["美食巡禮"],"s":40,"cu":"sandwich"},{"n":"いのまた","la":43.1991,"lo":140.99794,"c":"shop","t":["美食巡禮"],"s":40,"cu":"ピロシキ"},{"n":"不二家","la":43.18861,"lo":140.79072,"c":"shop","t":["美食巡禮"],"s":40},{"n":"三角市場","la":43.19854,"lo":140.99387,"c":"shop","t":["市場老街"],"s":90,"oh":"Mo-Su 07:00-16:00"},{"n":"夢市場","la":43.19691,"lo":140.99672,"c":"shop","s":90},{"n":"Mon Pierre","la":43.1962,"lo":140.99719,"c":"shop","t":["美食巡禮"],"s":40,"oh":"Mo-Sa 10:00-19:00"},{"n":"鱗友朝市","la":43.20867,"lo":140.99992,"c":"shop","t":["市場老街"],"s":90,"oh":"Mo-Sa 04:00-14:00"},{"n":"長崎屋小樽店","la":43.19778,"lo":140.99488,"c":"shop","s":90},{"n":"小樽市漁業協同組合地方卸売場","la":43.20581,"lo":140.99895,"c":"shop","t":["市場老街"],"s":90},{"n":"ラルズ","la":43.19227,"lo":140.79659,"c":"shop","s":90},{"n":"Bakery Ondine","la":43.1959,"lo":140.99741,"c":"shop","t":["美食巡禮"],"s":40},{"n":"まりんはうす","la":43.26053,"lo":140.65446,"c":"shop","t":["市場老街"],"s":40},{"n":"ノースランド","la":43.18506,"lo":140.78895,"c":"shop","t":["市場老街"],"s":40},{"n":"エルラプラザ","la":43.18693,"lo":140.79456,"c":"shop","t":["市場老街"],"s":40},{"n":"果実のふる里よいち","la":43.18629,"lo":140.79421,"c":"shop","s":90},{"n":"まるせんストアー","la":43.21761,"lo":140.96984,"c":"shop","s":90},{"n":"妙見市場","la":43.19272,"lo":140.99556,"c":"shop","t":["市場老街"],"s":90},{"n":"神威ファーム","la":43.30452,"lo":140.56258,"c":"shop","t":["美食巡禮"],"s":40},{"n":"東しゃこたん漁協市場","la":43.27257,"lo":140.63791,"c":"shop","s":90},{"n":"東しゃこたん直売所","la":43.27179,"lo":140.63727,"c":"shop","s":90},{"n":"松本商店","la":43.19392,"lo":140.99842,"c":"shop","s":90},{"n":"洋菓子 喫茶 米華堂","la":43.19396,"lo":140.99945,"c":"shop","t":["美食巡禮"],"s":40},{"n":"エグ・ヴィヴ","la":43.20499,"lo":140.8695,"c":"shop","t":["美食巡禮"],"s":40},{"n":"ラルズマート","la":43.18429,"lo":140.98816,"c":"shop","s":90},{"n":"マックスバリュ手宮店","la":43.20962,"lo":140.99995,"c":"shop","s":90},{"n":"入七八戸商店","la":43.29546,"lo":140.59993,"c":"shop","s":90},{"n":"北一硝子商品センター","la":43.20793,"lo":140.99992,"c":"shop","t":["市場老街"],"s":40},{"n":"コープ札幌オタモイ店","la":43.21398,"lo":140.95959,"c":"shop","s":90},{"n":"伊勢鮨","la":43.20058,"lo":140.99549,"c":"food","ad":"北海道小樽市稲穂3丁目","cu":"japanese","oh":"Th-Mo 11:30-14:30, 17:00-20:30","w":"https://www.isezushi.com/"},{"n":"小樽・蕎麦屋・籔半","la":43.19655,"lo":140.99587,"c":"food","ad":"北海道小樽市稲穂2丁目","cu":"soba","oh":"We-Mo 11:00-16:00, 16:30-20:30","w":"https://yabuhan.co.jp/"},{"n":"寿司和食 しかま","la":43.19324,"lo":140.99988,"c":"food","j":"寿司和食しかま","ad":"北海道小樽市花園1","cu":"sushi","oh":"Mo,We-Fr 11:00-15:00,17:00-21:00; Sa-Su 11:00-21:00","w":"http://www.shikamazushi.co.jp/"},{"n":"日本橋","la":43.19443,"lo":140.99948,"c":"food","ad":"北海道小樽市稲穂1","cu":"sushi","oh":"Fr-We 11:00-15:00(L.O. 14:30) 17:00-21:00(L.O. 20:30)","w":"http://www.otarusushi.com/"},{"n":"寿司和食しかま","la":43.19319,"lo":140.99986,"c":"food","ad":"北海道小樽市花園1","cu":"sushi","oh":"Mo,We-Fr 11:00-15:00 17:00-21:00, Sa-Su 11:00-21:00","w":"http://www.shikamazushi.co.jp"},{"n":"ニュー三幸","la":43.19514,"lo":140.99887,"c":"food","ad":"北海道小樽市稲穂1","cu":"regional","oh":"Mo-Su 11:30-21:00","w":"http://www.newsanko.jp/shop_otaru/index.html"},{"n":"お食事処　中村屋","la":43.35491,"lo":140.46505,"c":"food","ad":"北海道積丹町日司町","cu":"海鮮海鮮","oh":"Mo-Su 09:00-15:00","w":"https://www.nakamuraya.co"},{"n":"焼鳥 伊志井","la":43.1927,"lo":140.99791,"c":"food","ad":"北海道小樽市花園1","cu":"yakitori","oh":"Mo-Sa 17:00-22:00"},{"n":"ビストロ小泉","la":43.19461,"lo":140.99756,"c":"food","ad":"北海道小樽市稲穂1","cu":"regional","oh":"Mo-Su 11:30-21:00","w":"https://twitter.com/bistrot_koizumi"},{"n":"海鮮味処 御宿 新生","la":43.32812,"lo":140.37856,"c":"food","ad":"北海道積丹町大字余別町30番地","cu":"seafood","w":"http://www.syakotan.com/"},{"n":"海のや","la":43.32853,"lo":140.37889,"c":"food","ad":"北海道積丹町大字余別町30番地2","cu":"seafood","w":"http://uminoya.net/shakotan/index.html"},{"n":"ミスタードーナツ","la":43.19845,"lo":140.99476,"c":"food","cu":"donut","oh":"08:00-22:00"},{"n":"ケンタッキーフライドチキン","la":43.19858,"lo":140.99759,"c":"food","cu":"chicken","oh":"10:00-21:00"},{"n":"みよ福","la":43.19695,"lo":140.99736,"c":"food","cu":"sushi","oh":"Mo-Sa 12:00-21:00"},{"n":"バーガーキング","la":43.19809,"lo":140.99356,"c":"food","cu":"burger","oh":"Mo-Su 07:30-21:00"},{"n":"生蕎麦一福","la":43.19812,"lo":140.99975,"c":"food","cu":"noodle","w":"http://www.otaru-ichifuku.co.jp"},{"n":"ヴィクトリアステーション","la":43.20249,"lo":140.9963,"c":"food","ad":"北海道小樽市稲穂4丁目","cu":"steak_house","oh":"10:00-02:00"},{"n":"舊安田銀行","la":43.19962,"lo":140.99957,"c":"food","j":"花ごころ","cu":"sushi"},{"n":"なると","la":43.20028,"lo":140.99511,"c":"food","j":"なると本店","cu":"chicken;friture"},{"n":"みさき","la":43.3556,"lo":140.46473,"c":"food","j":"食事処みさき","cu":"ウニ丼_seafood"},{"n":"ほっともっと","la":43.19252,"lo":140.79245,"c":"food","cu":"japanese"},{"n":"モスバーガー","la":43.19545,"lo":140.99681,"c":"food","cu":"burger"},{"n":"すし処 貫","la":43.19298,"lo":140.99971,"c":"food","cu":"sushi","oh":"Fr-We 11:30-13:00, 14:00-15:00"},{"n":"三四郎","la":43.19268,"lo":140.99997,"c":"food","cu":"meat","oh":"Tu-Fr 17:00-25:30, Sa-Su 16:30-25:00, PH 16:30-22:30"},{"n":"都寿司","la":43.19004,"lo":140.99986,"c":"food","cu":"sushi","oh":"We-Mo 12:30-22:00"},{"n":"堀食堂","la":43.26229,"lo":140.64031,"c":"food","ad":"北海道古平町浜町","cu":"japanese"},{"n":"勝栄鮨","la":43.14369,"lo":140.43181,"c":"food","oh":"Tu-Su 11:00-15:00"},{"n":"アンディアモ","la":43.19612,"lo":140.99638,"c":"food","cu":"italian"},{"n":"ピザハット","la":43.19956,"lo":140.99947,"c":"food","cu":"pizza"},{"n":"浜寿し","la":43.3279,"lo":140.38083,"c":"food","ad":"北海道積丹町大字余別町9番地12"},{"n":"魚真","la":43.19785,"lo":140.99845,"c":"food","cu":"sushi"},{"n":"焼肉 寿楽園","la":43.1912,"lo":140.99859,"c":"food","ad":"小樽市花園1丁目","cu":"steak_house"},{"n":"みどりや","la":43.18918,"lo":140.79253,"c":"food","cu":"sushi"},{"n":"海鮮工房かきざき","la":43.18642,"lo":140.79305,"c":"food","j":"柿崎商店","cu":"seafood"},{"n":"食事処たけや","la":43.18877,"lo":140.79075,"c":"food","j":"たけや","cu":"seafood"},{"n":"せいちゃん","la":43.1863,"lo":140.79357,"c":"food","cu":"ramen"},{"n":"ヨイッチーニ","la":43.19249,"lo":140.8011,"c":"food","cu":"Poise,pasta,etc."},{"n":"余市ワイナリー　カフェ&ベーカリー","la":43.16896,"lo":140.79214,"c":"food","j":"余市ワイナリー","cu":"ice_cream"},{"n":"道の駅あかいがわ","la":43.05142,"lo":140.84442,"c":"food","cu":"ramen;curry;soba;ice_cream"},{"n":"Takinami","la":43.19849,"lo":140.99411,"c":"food","j":"滝波商店","cu":"seafood"},{"n":"頂","la":43.19562,"lo":140.99674,"c":"food","cu":"barbecue"},{"n":"串鳥","la":43.19513,"lo":140.99565,"c":"food","cu":"japanese;chicken"},{"n":"桂苑","la":43.19635,"lo":140.99684,"c":"food","cu":"chinese"},{"n":"すし勘","la":43.1939,"lo":140.9995,"c":"food","cu":"sushi"},{"n":"おたる屋台村 レンガ横丁・ろまん横丁","la":43.19533,"lo":140.99835,"c":"food","w":"http://otaruyataimura.jp/"},{"n":"渡海家","la":43.19865,"lo":140.99559,"c":"food","cu":"noodle"},{"n":"ブラッキー","la":43.19299,"lo":140.99972,"c":"food"},{"n":"カラオケ ルルル","la":43.1913,"lo":140.9991,"c":"food","oh":"Mo-Tu, Th-Sa 11:00-17:00, 19:00-22:00"},{"n":"ミッシェル","la":43.19182,"lo":140.99827,"c":"food"},{"n":"焼肉丼もの まるた","la":43.19364,"lo":140.99808,"c":"food","oh":"Mo-Su 17:00-22:00"},{"n":"そば 信州屋支店","la":43.19136,"lo":140.99938,"c":"food","cu":"soba;udon;ramen"},{"n":"ラーメン 龍王","la":43.193,"lo":140.99901,"c":"food","cu":"ramen"},{"n":"アンリミテッド","la":43.19189,"lo":140.99839,"c":"food"},{"n":"待夢尚","la":43.19329,"lo":140.99808,"c":"food","oh":"Mo-Su 16:00-22:00"},{"n":"中華料理 五香飯店","la":43.19299,"lo":140.99812,"c":"food"},{"n":"宝すし","la":43.19198,"lo":140.99836,"c":"food","cu":"sushi"},{"n":"華舟","la":43.19101,"lo":140.99938,"c":"food","cu":"chinese"},{"n":"た志満","la":43.19108,"lo":140.99932,"c":"food","cu":"sushi"},{"n":"雅叙園","la":43.19106,"lo":140.99913,"c":"food","cu":"sushi"},{"n":"純喫茶 光","la":43.19754,"lo":140.99647,"c":"food"},{"n":"Marie Laurencin","la":43.19823,"lo":140.99472,"c":"food","oh":"08:00-20:00"},{"n":"サトウブレンドビアンカフェ","la":43.18904,"lo":140.99727,"c":"food","oh":"Mo-Sa 11:00-19:00"},{"n":"生うに丼のなぎさ","la":43.32985,"lo":140.39609,"c":"food","cu":"seafood"},{"n":"Cotaru","la":43.1991,"lo":140.99789,"c":"food","oh":"Mo-Su 09:00-19:00"},{"n":"冨久寿司","la":43.2967,"lo":140.59948,"c":"food","cu":"japanese;sushi"},{"n":"カムイ番屋","la":43.32808,"lo":140.35772,"c":"food","cu":"regional"},{"n":"ふじ鮨","la":43.29787,"lo":140.59714,"c":"food","cu":"regional"},{"n":"籔半","la":43.19654,"lo":140.99595,"c":"food","cu":"japanese"},{"n":"山の猿","la":43.19784,"lo":140.99555,"c":"food","cu":"regional;japanese"},{"n":"ファミリーすし ガーデンハウス","la":43.18596,"lo":140.79735,"c":"food","cu":"sushi"},{"n":"鮨ブッフェダイニングふじ","la":43.19289,"lo":140.80085,"c":"food","cu":"japanese"},{"n":"千成ラーメン","la":43.19195,"lo":140.80033,"c":"food","cu":"noodle"},{"n":"シャロン","la":43.19844,"lo":140.99559,"c":"food"},{"n":"鱗晃","la":43.37122,"lo":140.4768,"c":"food"},{"n":"つどい","la":43.19444,"lo":140.99921,"c":"food"},{"n":"ろまん横丁","la":43.19549,"lo":140.99859,"c":"food"},{"n":"しろくま食堂","la":43.20644,"lo":140.9989,"c":"food"},{"n":"館","la":43.19347,"lo":140.99943,"c":"food"},{"n":"うに膳屋","la":43.3659,"lo":140.47162,"c":"food"},{"n":"南保留太郎商店","la":43.20888,"lo":140.7737,"c":"food"},{"n":"純の店","la":43.29655,"lo":140.59783,"c":"food"},{"n":"田村岩太郎商店","la":43.29648,"lo":140.59909,"c":"food"},{"n":"新家寿司","la":43.27793,"lo":140.63846,"c":"food"},{"n":"港寿司","la":43.27826,"lo":140.63779,"c":"food","j":"港寿し"},{"n":"庄坊番屋","la":43.19069,"lo":140.99701,"c":"food"},{"n":"レストラン樽","la":43.18542,"lo":140.78911,"c":"food"},{"n":"燻香廊","la":43.20849,"lo":140.77379,"c":"food"},{"n":"麻ほろ","la":43.19819,"lo":140.99942,"c":"food"},{"n":"とりあえず","la":43.19346,"lo":140.99783,"c":"food"},{"n":"ふじりん","la":43.1931,"lo":140.99946,"c":"food"},{"n":"ウイング","la":43.19311,"lo":140.99943,"c":"food"},{"n":"食堂 パサール食堂","la":43.19136,"lo":140.99913,"c":"food"},{"n":"北ぢぞう","la":43.1915,"lo":140.99989,"c":"food"},{"n":"焼肉・ホルモン しちりん","la":43.19151,"lo":140.99995,"c":"food"},{"n":"郷土料理 鶴間","la":43.19382,"lo":140.9989,"c":"food"},{"n":"RUCE","la":43.19184,"lo":140.99833,"c":"food"},{"n":"Blue moon","la":43.19185,"lo":140.99835,"c":"food"},{"n":"Bijou","la":43.19183,"lo":140.99829,"c":"food"},{"n":"結華","la":43.19186,"lo":140.9984,"c":"food"},{"n":"N.J","la":43.19187,"lo":140.99842,"c":"food"},{"n":"カラオケ 二輪草","la":43.19187,"lo":140.99844,"c":"food"},{"n":"ナイトイン Beliver","la":43.19198,"lo":140.99902,"c":"food"},{"n":"よしみんち","la":43.19197,"lo":140.999,"c":"food"},{"n":"DESPERA","la":43.19379,"lo":140.99901,"c":"food"},{"n":"焼肉 地酒の店 飯ぬ酒","la":43.19175,"lo":140.99842,"c":"food"},{"n":"幸寿司","la":43.19366,"lo":140.99893,"c":"food"},{"n":"おでん・焼物 はつ花","la":43.19398,"lo":140.99983,"c":"food"},{"n":"庵","la":43.19357,"lo":140.999,"c":"food"},{"n":"ベラ","la":43.19191,"lo":140.99855,"c":"food"},{"n":"居酒屋スナック なおみ","la":43.19171,"lo":140.99831,"c":"food"},{"n":"郷土料理 おおとみ","la":43.1936,"lo":140.99911,"c":"food"},{"n":"ダイニング ボア","la":43.19344,"lo":140.99837,"c":"food"},{"n":"食べ呑み家 さいとうさんち","la":43.19349,"lo":140.99834,"c":"food"},{"n":"美菱会館","la":43.19416,"lo":140.99992,"c":"food"},{"n":"PublicLiveBar Y's","la":43.19182,"lo":140.9983,"c":"food"},{"n":"樽","la":43.19183,"lo":140.99833,"c":"food"},{"n":"柳助","la":43.1933,"lo":140.99793,"c":"food"},{"n":"小樽おやじ本舗","la":43.193,"lo":140.99942,"c":"food"},{"n":"味処 あこやん","la":43.19287,"lo":140.99921,"c":"food"},{"n":"立風","la":43.19278,"lo":140.99924,"c":"food"},{"n":"スナック純","la":43.19274,"lo":140.99911,"c":"food"},{"n":"小樽魚亭","la":43.19301,"lo":140.99856,"c":"food"},{"n":"のんのん","la":43.19272,"lo":140.9995,"c":"food"},{"n":"スナック グランドハワイ","la":43.19248,"lo":140.99928,"c":"food"},{"n":"酒のちごはん時々〆パフェ きぶんしだい","la":43.1931,"lo":140.99932,"c":"food"},{"n":"sun&peace","la":43.19184,"lo":140.99868,"c":"food"},{"n":"ザパラダイス","la":43.19186,"lo":140.99872,"c":"food","j":"ザ パラダイス"},{"n":"スナック NEO","la":43.19189,"lo":140.99882,"c":"food"},{"n":"聖徳太子","la":43.19196,"lo":140.99898,"c":"food"},{"n":"寿司・居酒屋 はっかく","la":43.19339,"lo":140.99788,"c":"food"},{"n":"おたる 魚亭","la":43.19303,"lo":140.99858,"c":"food"},{"n":"夢の","la":43.19321,"lo":140.99819,"c":"food"},{"n":"あき","la":43.19316,"lo":140.99834,"c":"food"},{"n":"まる","la":43.19313,"lo":140.99836,"c":"food"},{"n":"うらら","la":43.19183,"lo":140.9989,"c":"food"},{"n":"清寿司","la":43.19167,"lo":140.99917,"c":"food"},{"n":"すなっく マーメイド","la":43.19177,"lo":140.99896,"c":"food"},{"n":"コイン","la":43.192,"lo":140.9991,"c":"food"},{"n":"北斗","la":43.19301,"lo":140.99946,"c":"food"},{"n":"すなっく愛","la":43.19284,"lo":140.99887,"c":"food"},{"n":"かまわぬ","la":43.19298,"lo":140.99845,"c":"food"},{"n":"みはる","la":43.19281,"lo":140.99911,"c":"food"},{"n":"スナックヴェナ","la":43.19268,"lo":140.99846,"c":"food"},{"n":"ねんきん酒場","la":43.19329,"lo":140.99824,"c":"food"},{"n":"わか松","la":43.19319,"lo":140.99832,"c":"food"},{"n":"幸ちゃん","la":43.19321,"lo":140.99832,"c":"food"},{"n":"The COAST","la":43.19304,"lo":140.9983,"c":"food"},{"n":"杉","la":43.19306,"lo":140.99841,"c":"food"},{"n":"パサール食堂","la":43.19134,"lo":140.99914,"c":"food"},{"n":"スナック 杉","la":43.19304,"lo":140.99843,"c":"food"},{"n":"あらき","la":43.1924,"lo":140.99988,"c":"food"},{"n":"楽々亭ラーメン","la":43.19235,"lo":140.99977,"c":"food"},{"n":"ウイッチ","la":43.19286,"lo":140.99852,"c":"food"},{"n":"おれの店","la":43.19237,"lo":140.99983,"c":"food"},{"n":"鉄板焼 真や","la":43.19257,"lo":140.99924,"c":"food"},{"n":"焼鳥ささき","la":43.19392,"lo":140.99965,"c":"food"},{"n":"寿司 達","la":43.19213,"lo":140.99904,"c":"food"},{"n":"プリンセスハート","la":43.19242,"lo":140.99997,"c":"food"},{"n":"スナック GOLD","la":43.19251,"lo":140.99968,"c":"food"},{"n":"とんちんかん酒場鈴木笑店","la":43.19258,"lo":140.99964,"c":"food"},{"n":"Day by Day","la":43.19266,"lo":140.99941,"c":"food"},{"n":"B.LOOP","la":43.19259,"lo":140.99926,"c":"food"},{"n":"ディアナ","la":43.1925,"lo":140.99913,"c":"food"},{"n":"ここ家","la":43.19253,"lo":140.99911,"c":"food"},{"n":"フルハウス","la":43.19254,"lo":140.99913,"c":"food"},{"n":"まりこの巣なっく","la":43.19255,"lo":140.99916,"c":"food"},{"n":"スナック クレージュ","la":43.19255,"lo":140.99909,"c":"food"},{"n":"スナック 霧子","la":43.19235,"lo":140.99905,"c":"food"},{"n":"郷土料理 江差亭","la":43.19234,"lo":140.99885,"c":"food"},{"n":"ラーメン右衛門","la":43.19305,"lo":140.99997,"c":"food"},{"n":"マスカレード","la":43.1924,"lo":140.99991,"c":"food"},{"n":"スナック 雅夢","la":43.19251,"lo":140.99915,"c":"food"},{"n":"串焼大将","la":43.19021,"lo":140.99912,"c":"food"},{"n":"たじぺい","la":43.1905,"lo":140.99952,"c":"food"},{"n":"純","la":43.19062,"lo":140.99982,"c":"food"},{"n":"Free Will","la":43.19581,"lo":140.99636,"c":"food"},{"n":"食堂うしお","la":43.32992,"lo":140.36571,"c":"food"},{"n":"食べ処あい田","la":43.19839,"lo":140.99388,"c":"food"},{"n":"初音","la":43.19744,"lo":140.99607,"c":"food"},{"n":"Nishiya ramen (2F)","la":43.1984,"lo":140.99416,"c":"food"},{"n":"ホピの丘","la":43.09083,"lo":140.97443,"c":"food"},{"n":"お食事処見はらし亭","la":43.18845,"lo":140.99303,"c":"food"},{"n":"ビラリストランテGAJA小樽店","la":43.20489,"lo":140.9983,"c":"food","j":"GAJA"},{"n":"山中牧場","la":43.08667,"lo":140.91983,"c":"food"},{"n":"春香園","la":43.19683,"lo":140.99619,"c":"food"},{"n":"フルティコ 余市店","la":43.19242,"lo":140.80095,"c":"food"},{"n":"cafe di lode","la":43.18703,"lo":140.83349,"c":"food"}]